package com.google.android.gms.ads.internal.request;

import java.io.OutputStream;

final class b
  implements Runnable
{
  b(LargeParcelTeleporter paramLargeParcelTeleporter, OutputStream paramOutputStream, byte[] paramArrayOfByte)
  {
  }

  // ERROR //
  public final void run()
  {
    // Byte code:
    //   0: new 24	java/io/DataOutputStream
    //   3: dup
    //   4: aload_0
    //   5: getfield 14	com/google/android/gms/ads/internal/request/b:a	Ljava/io/OutputStream;
    //   8: invokespecial 27	java/io/DataOutputStream:<init>	(Ljava/io/OutputStream;)V
    //   11: astore_1
    //   12: aload_1
    //   13: aload_0
    //   14: getfield 16	com/google/android/gms/ads/internal/request/b:b	[B
    //   17: arraylength
    //   18: invokevirtual 31	java/io/DataOutputStream:writeInt	(I)V
    //   21: aload_1
    //   22: aload_0
    //   23: getfield 16	com/google/android/gms/ads/internal/request/b:b	[B
    //   26: invokevirtual 35	java/io/DataOutputStream:write	([B)V
    //   29: aload_1
    //   30: invokestatic 40	android/support/v4/app/j:a	(Ljava/io/Closeable;)V
    //   33: return
    //   34: astore_2
    //   35: aconst_null
    //   36: astore_1
    //   37: ldc 42
    //   39: aload_2
    //   40: invokestatic 47	com/google/android/gms/b/hc:b	(Ljava/lang/String;Ljava/lang/Throwable;)V
    //   43: invokestatic 53	com/google/android/gms/ads/internal/P:h	()Lcom/google/android/gms/b/hn;
    //   46: aload_2
    //   47: iconst_1
    //   48: invokevirtual 58	com/google/android/gms/b/hn:a	(Ljava/lang/Throwable;Z)V
    //   51: aload_1
    //   52: ifnonnull +11 -> 63
    //   55: aload_0
    //   56: getfield 14	com/google/android/gms/ads/internal/request/b:a	Ljava/io/OutputStream;
    //   59: invokestatic 40	android/support/v4/app/j:a	(Ljava/io/Closeable;)V
    //   62: return
    //   63: aload_1
    //   64: invokestatic 40	android/support/v4/app/j:a	(Ljava/io/Closeable;)V
    //   67: return
    //   68: astore_3
    //   69: aconst_null
    //   70: astore_1
    //   71: aload_1
    //   72: ifnonnull +12 -> 84
    //   75: aload_0
    //   76: getfield 14	com/google/android/gms/ads/internal/request/b:a	Ljava/io/OutputStream;
    //   79: invokestatic 40	android/support/v4/app/j:a	(Ljava/io/Closeable;)V
    //   82: aload_3
    //   83: athrow
    //   84: aload_1
    //   85: invokestatic 40	android/support/v4/app/j:a	(Ljava/io/Closeable;)V
    //   88: goto -6 -> 82
    //   91: astore_3
    //   92: goto -21 -> 71
    //   95: astore_2
    //   96: goto -59 -> 37
    //
    // Exception table:
    //   from	to	target	type
    //   0	12	34	java/io/IOException
    //   0	12	68	finally
    //   12	29	91	finally
    //   37	51	91	finally
    //   12	29	95	java/io/IOException
  }
}

/* Location:           C:\Users\KSHITIZ GUPTA\Downloads\apktool-install-windws\dex2jar-0.0.9.15\dex2jar-0.0.9.15\classes_dex2jar.jar
 * Qualified Name:     com.google.android.gms.ads.internal.request.b
 * JD-Core Version:    0.6.0
 */