package com.google.android.gms.b;

public final class ci extends ha
{
  private final String a;
  private final is b;

  public ci(is paramis, String paramString)
  {
    this.b = paramis;
    this.a = paramString;
  }

  // ERROR //
  public final void a()
  {
    // Byte code:
    //   0: iconst_0
    //   1: istore_1
    //   2: aload_0
    //   3: getfield 17	com/google/android/gms/b/ci:a	Ljava/lang/String;
    //   6: astore_2
    //   7: iload_1
    //   8: bipush 10
    //   10: if_icmpge +453 -> 463
    //   13: iload_1
    //   14: iconst_1
    //   15: iadd
    //   16: istore 9
    //   18: new 25	java/net/URL
    //   21: dup
    //   22: aload_2
    //   23: invokespecial 28	java/net/URL:<init>	(Ljava/lang/String;)V
    //   26: astore 10
    //   28: ldc 30
    //   30: aload 10
    //   32: invokevirtual 34	java/net/URL:getHost	()Ljava/lang/String;
    //   35: invokevirtual 40	java/lang/String:equalsIgnoreCase	(Ljava/lang/String;)Z
    //   38: istore 17
    //   40: iload 17
    //   42: ifeq +57 -> 99
    //   45: aload_2
    //   46: astore_3
    //   47: aload_3
    //   48: invokestatic 46	android/net/Uri:parse	(Ljava/lang/String;)Landroid/net/Uri;
    //   51: astore 4
    //   53: new 48	android/content/Intent
    //   56: dup
    //   57: ldc 50
    //   59: invokespecial 51	android/content/Intent:<init>	(Ljava/lang/String;)V
    //   62: astore 5
    //   64: aload 5
    //   66: ldc 52
    //   68: invokevirtual 56	android/content/Intent:addFlags	(I)Landroid/content/Intent;
    //   71: pop
    //   72: aload 5
    //   74: aload 4
    //   76: invokevirtual 60	android/content/Intent:setData	(Landroid/net/Uri;)Landroid/content/Intent;
    //   79: pop
    //   80: invokestatic 66	com/google/android/gms/ads/internal/P:e	()Lcom/google/android/gms/b/hu;
    //   83: pop
    //   84: aload_0
    //   85: getfield 15	com/google/android/gms/b/ci:b	Lcom/google/android/gms/b/is;
    //   88: invokeinterface 72 1 0
    //   93: aload 5
    //   95: invokestatic 77	com/google/android/gms/b/hu:a	(Landroid/content/Context;Landroid/content/Intent;)V
    //   98: return
    //   99: ldc 79
    //   101: aload 10
    //   103: invokevirtual 82	java/net/URL:getProtocol	()Ljava/lang/String;
    //   106: invokevirtual 40	java/lang/String:equalsIgnoreCase	(Ljava/lang/String;)Z
    //   109: ifeq +8 -> 117
    //   112: aload_2
    //   113: astore_3
    //   114: goto -67 -> 47
    //   117: aload 10
    //   119: invokevirtual 86	java/net/URL:openConnection	()Ljava/net/URLConnection;
    //   122: checkcast 88	java/net/HttpURLConnection
    //   125: astore 18
    //   127: invokestatic 66	com/google/android/gms/ads/internal/P:e	()Lcom/google/android/gms/b/hu;
    //   130: aload_0
    //   131: getfield 15	com/google/android/gms/b/ci:b	Lcom/google/android/gms/b/is;
    //   134: invokeinterface 72 1 0
    //   139: aload_0
    //   140: getfield 15	com/google/android/gms/b/ci:b	Lcom/google/android/gms/b/is;
    //   143: invokeinterface 92 1 0
    //   148: getfield 96	com/google/android/gms/ads/internal/util/client/VersionInfoParcel:b	Ljava/lang/String;
    //   151: iconst_0
    //   152: aload 18
    //   154: invokevirtual 99	com/google/android/gms/b/hu:a	(Landroid/content/Context;Ljava/lang/String;ZLjava/net/HttpURLConnection;)V
    //   157: aload 18
    //   159: invokevirtual 103	java/net/HttpURLConnection:getResponseCode	()I
    //   162: istore 20
    //   164: aload 18
    //   166: invokevirtual 107	java/net/HttpURLConnection:getHeaderFields	()Ljava/util/Map;
    //   169: astore 21
    //   171: iload 20
    //   173: sipush 300
    //   176: if_icmplt +280 -> 456
    //   179: iload 20
    //   181: sipush 399
    //   184: if_icmpgt +272 -> 456
    //   187: aload 21
    //   189: ldc 109
    //   191: invokeinterface 115 2 0
    //   196: ifeq +68 -> 264
    //   199: aload 21
    //   201: ldc 109
    //   203: invokeinterface 119 2 0
    //   208: checkcast 121	java/util/List
    //   211: astore 27
    //   213: aload 27
    //   215: ifnull +241 -> 456
    //   218: aload 27
    //   220: invokeinterface 124 1 0
    //   225: ifle +231 -> 456
    //   228: aload 27
    //   230: iconst_0
    //   231: invokeinterface 127 2 0
    //   236: checkcast 36	java/lang/String
    //   239: astore 22
    //   241: aload 22
    //   243: invokestatic 133	android/text/TextUtils:isEmpty	(Ljava/lang/CharSequence;)Z
    //   246: ifeq +54 -> 300
    //   249: ldc 135
    //   251: invokestatic 140	com/google/android/gms/b/hc:d	(Ljava/lang/String;)V
    //   254: aload 18
    //   256: invokevirtual 143	java/net/HttpURLConnection:disconnect	()V
    //   259: aload_2
    //   260: astore_3
    //   261: goto -214 -> 47
    //   264: aload 21
    //   266: ldc 145
    //   268: invokeinterface 115 2 0
    //   273: istore 26
    //   275: aconst_null
    //   276: astore 27
    //   278: iload 26
    //   280: ifeq -67 -> 213
    //   283: aload 21
    //   285: ldc 145
    //   287: invokeinterface 119 2 0
    //   292: checkcast 121	java/util/List
    //   295: astore 27
    //   297: goto -84 -> 213
    //   300: aload 18
    //   302: invokevirtual 143	java/net/HttpURLConnection:disconnect	()V
    //   305: iload 9
    //   307: istore_1
    //   308: aload 22
    //   310: astore_2
    //   311: goto -304 -> 7
    //   314: astore 19
    //   316: aload 18
    //   318: invokevirtual 143	java/net/HttpURLConnection:disconnect	()V
    //   321: aload 19
    //   323: athrow
    //   324: astore 15
    //   326: aload 15
    //   328: astore 16
    //   330: aload_2
    //   331: astore_3
    //   332: new 147	java/lang/StringBuilder
    //   335: dup
    //   336: ldc 149
    //   338: invokespecial 150	java/lang/StringBuilder:<init>	(Ljava/lang/String;)V
    //   341: aload_3
    //   342: invokevirtual 154	java/lang/StringBuilder:append	(Ljava/lang/String;)Ljava/lang/StringBuilder;
    //   345: invokevirtual 157	java/lang/StringBuilder:toString	()Ljava/lang/String;
    //   348: aload 16
    //   350: invokestatic 161	com/google/android/gms/b/hc:c	(Ljava/lang/String;Ljava/lang/Throwable;)V
    //   353: goto -306 -> 47
    //   356: astore 13
    //   358: aload 13
    //   360: astore 14
    //   362: aload_2
    //   363: astore_3
    //   364: new 147	java/lang/StringBuilder
    //   367: dup
    //   368: ldc 163
    //   370: invokespecial 150	java/lang/StringBuilder:<init>	(Ljava/lang/String;)V
    //   373: aload_3
    //   374: invokevirtual 154	java/lang/StringBuilder:append	(Ljava/lang/String;)Ljava/lang/StringBuilder;
    //   377: invokevirtual 157	java/lang/StringBuilder:toString	()Ljava/lang/String;
    //   380: aload 14
    //   382: invokestatic 161	com/google/android/gms/b/hc:c	(Ljava/lang/String;Ljava/lang/Throwable;)V
    //   385: goto -338 -> 47
    //   388: astore 11
    //   390: aload 11
    //   392: astore 12
    //   394: aload_2
    //   395: astore_3
    //   396: new 147	java/lang/StringBuilder
    //   399: dup
    //   400: ldc 163
    //   402: invokespecial 150	java/lang/StringBuilder:<init>	(Ljava/lang/String;)V
    //   405: aload_3
    //   406: invokevirtual 154	java/lang/StringBuilder:append	(Ljava/lang/String;)Ljava/lang/StringBuilder;
    //   409: invokevirtual 157	java/lang/StringBuilder:toString	()Ljava/lang/String;
    //   412: aload 12
    //   414: invokestatic 161	com/google/android/gms/b/hc:c	(Ljava/lang/String;Ljava/lang/Throwable;)V
    //   417: goto -370 -> 47
    //   420: astore 25
    //   422: aload 22
    //   424: astore_3
    //   425: aload 25
    //   427: astore 12
    //   429: goto -33 -> 396
    //   432: astore 24
    //   434: aload 22
    //   436: astore_3
    //   437: aload 24
    //   439: astore 14
    //   441: goto -77 -> 364
    //   444: astore 23
    //   446: aload 22
    //   448: astore_3
    //   449: aload 23
    //   451: astore 16
    //   453: goto -121 -> 332
    //   456: ldc 165
    //   458: astore 22
    //   460: goto -219 -> 241
    //   463: aload_2
    //   464: astore_3
    //   465: goto -418 -> 47
    //
    // Exception table:
    //   from	to	target	type
    //   127	171	314	finally
    //   187	213	314	finally
    //   218	241	314	finally
    //   241	254	314	finally
    //   264	275	314	finally
    //   283	297	314	finally
    //   18	40	324	java/lang/IndexOutOfBoundsException
    //   99	112	324	java/lang/IndexOutOfBoundsException
    //   117	127	324	java/lang/IndexOutOfBoundsException
    //   254	259	324	java/lang/IndexOutOfBoundsException
    //   316	324	324	java/lang/IndexOutOfBoundsException
    //   18	40	356	java/io/IOException
    //   99	112	356	java/io/IOException
    //   117	127	356	java/io/IOException
    //   254	259	356	java/io/IOException
    //   316	324	356	java/io/IOException
    //   18	40	388	java/lang/RuntimeException
    //   99	112	388	java/lang/RuntimeException
    //   117	127	388	java/lang/RuntimeException
    //   254	259	388	java/lang/RuntimeException
    //   316	324	388	java/lang/RuntimeException
    //   300	305	420	java/lang/RuntimeException
    //   300	305	432	java/io/IOException
    //   300	305	444	java/lang/IndexOutOfBoundsException
  }

  public final void b()
  {
  }
}

/* Location:           C:\Users\KSHITIZ GUPTA\Downloads\apktool-install-windws\dex2jar-0.0.9.15\dex2jar-0.0.9.15\classes_dex2jar.jar
 * Qualified Name:     com.google.android.gms.b.ci
 * JD-Core Version:    0.6.0
 */