package com.google.android.gms.b;

import android.content.Context;
import java.io.File;
import java.text.DecimalFormat;
import java.util.Collections;
import java.util.HashSet;
import java.util.Set;

public final class cw extends cq
{
  private static final Set b = Collections.synchronizedSet(new HashSet());
  private static final DecimalFormat c = new DecimalFormat("#,###");
  private File d;
  private boolean e;

  public cw(is paramis)
  {
    super(paramis);
    File localFile = this.a.getCacheDir();
    if (localFile == null)
      hc.d("Context.getCacheDir() returned null");
    do
    {
      return;
      this.d = new File(localFile, "admobVideoStreams");
      if ((this.d.isDirectory()) || (this.d.mkdirs()))
        continue;
      hc.d("Could not create preload cache directory at " + this.d.getAbsolutePath());
      this.d = null;
      return;
    }
    while ((this.d.setReadable(true, false)) && (this.d.setExecutable(true, false)));
    hc.d("Could not set cache file permissions at " + this.d.getAbsolutePath());
    this.d = null;
  }

  private File a(File paramFile)
  {
    return new File(this.d, paramFile.getName() + ".done");
  }

  // ERROR //
  public final boolean a(java.lang.String paramString)
  {
    // Byte code:
    //   0: aload_0
    //   1: getfield 64	com/google/android/gms/b/cw:d	Ljava/io/File;
    //   4: ifnonnull +14 -> 18
    //   7: aload_0
    //   8: aload_1
    //   9: aconst_null
    //   10: ldc 112
    //   12: aconst_null
    //   13: invokevirtual 115	com/google/android/gms/b/cw:a	(Ljava/lang/String;Ljava/lang/String;Ljava/lang/String;Ljava/lang/String;)V
    //   16: iconst_0
    //   17: ireturn
    //   18: aload_0
    //   19: getfield 64	com/google/android/gms/b/cw:d	Ljava/io/File;
    //   22: ifnonnull +61 -> 83
    //   25: iconst_0
    //   26: istore 6
    //   28: getstatic 121	com/google/android/gms/b/aD:g	Lcom/google/android/gms/b/au;
    //   31: astore 7
    //   33: iload 6
    //   35: invokestatic 127	com/google/android/gms/ads/internal/P:n	()Lcom/google/android/gms/b/aB;
    //   38: aload 7
    //   40: invokevirtual 132	com/google/android/gms/b/aB:a	(Lcom/google/android/gms/b/au;)Ljava/lang/Object;
    //   43: checkcast 134	java/lang/Integer
    //   46: invokevirtual 138	java/lang/Integer:intValue	()I
    //   49: if_icmple +224 -> 273
    //   52: aload_0
    //   53: getfield 64	com/google/android/gms/b/cw:d	Ljava/io/File;
    //   56: ifnonnull +81 -> 137
    //   59: iconst_0
    //   60: istore 70
    //   62: iload 70
    //   64: ifne -46 -> 18
    //   67: ldc 140
    //   69: invokestatic 55	com/google/android/gms/b/hc:d	(Ljava/lang/String;)V
    //   72: aload_0
    //   73: aload_1
    //   74: aconst_null
    //   75: ldc 142
    //   77: aconst_null
    //   78: invokevirtual 115	com/google/android/gms/b/cw:a	(Ljava/lang/String;Ljava/lang/String;Ljava/lang/String;Ljava/lang/String;)V
    //   81: iconst_0
    //   82: ireturn
    //   83: aload_0
    //   84: getfield 64	com/google/android/gms/b/cw:d	Ljava/io/File;
    //   87: invokevirtual 146	java/io/File:listFiles	()[Ljava/io/File;
    //   90: astore_2
    //   91: aload_2
    //   92: arraylength
    //   93: istore_3
    //   94: iconst_0
    //   95: istore 4
    //   97: iconst_0
    //   98: istore 5
    //   100: iload 5
    //   102: iload_3
    //   103: if_icmpge +27 -> 130
    //   106: aload_2
    //   107: iload 5
    //   109: aaload
    //   110: invokevirtual 101	java/io/File:getName	()Ljava/lang/String;
    //   113: ldc 103
    //   115: invokevirtual 151	java/lang/String:endsWith	(Ljava/lang/String;)Z
    //   118: ifne +6 -> 124
    //   121: iinc 4 1
    //   124: iinc 5 1
    //   127: goto -27 -> 100
    //   130: iload 4
    //   132: istore 6
    //   134: goto -106 -> 28
    //   137: aconst_null
    //   138: astore 64
    //   140: ldc2_w 152
    //   143: lstore 65
    //   145: aload_0
    //   146: getfield 64	com/google/android/gms/b/cw:d	Ljava/io/File;
    //   149: invokevirtual 146	java/io/File:listFiles	()[Ljava/io/File;
    //   152: astore 67
    //   154: aload 67
    //   156: arraylength
    //   157: istore 68
    //   159: iconst_0
    //   160: istore 69
    //   162: iload 69
    //   164: iload 68
    //   166: if_icmpge +63 -> 229
    //   169: aload 67
    //   171: iload 69
    //   173: aaload
    //   174: astore 72
    //   176: aload 72
    //   178: invokevirtual 101	java/io/File:getName	()Ljava/lang/String;
    //   181: ldc 103
    //   183: invokevirtual 151	java/lang/String:endsWith	(Ljava/lang/String;)Z
    //   186: ifne +1369 -> 1555
    //   189: aload 72
    //   191: invokevirtual 157	java/io/File:lastModified	()J
    //   194: lstore 73
    //   196: lload 73
    //   198: lload 65
    //   200: lcmp
    //   201: ifge +1354 -> 1555
    //   204: aload 72
    //   206: astore 75
    //   208: iload 69
    //   210: iconst_1
    //   211: iadd
    //   212: istore 76
    //   214: aload 75
    //   216: astore 64
    //   218: iload 76
    //   220: istore 69
    //   222: lload 73
    //   224: lstore 65
    //   226: goto -64 -> 162
    //   229: iconst_0
    //   230: istore 70
    //   232: aload 64
    //   234: ifnull -172 -> 62
    //   237: aload 64
    //   239: invokevirtual 160	java/io/File:delete	()Z
    //   242: istore 70
    //   244: aload_0
    //   245: aload 64
    //   247: invokespecial 162	com/google/android/gms/b/cw:a	(Ljava/io/File;)Ljava/io/File;
    //   250: astore 71
    //   252: aload 71
    //   254: invokevirtual 165	java/io/File:isFile	()Z
    //   257: ifeq -195 -> 62
    //   260: iload 70
    //   262: aload 71
    //   264: invokevirtual 160	java/io/File:delete	()Z
    //   267: iand
    //   268: istore 70
    //   270: goto -208 -> 62
    //   273: invokestatic 170	com/google/android/gms/ads/internal/client/x:a	()Lcom/google/android/gms/ads/internal/util/client/a;
    //   276: pop
    //   277: aload_1
    //   278: invokestatic 175	com/google/android/gms/ads/internal/util/client/a:a	(Ljava/lang/String;)Ljava/lang/String;
    //   281: astore 9
    //   283: new 57	java/io/File
    //   286: dup
    //   287: aload_0
    //   288: getfield 64	com/google/android/gms/b/cw:d	Ljava/io/File;
    //   291: aload 9
    //   293: invokespecial 62	java/io/File:<init>	(Ljava/io/File;Ljava/lang/String;)V
    //   296: astore 10
    //   298: aload_0
    //   299: aload 10
    //   301: invokespecial 162	com/google/android/gms/b/cw:a	(Ljava/io/File;)Ljava/io/File;
    //   304: astore 11
    //   306: aload 10
    //   308: invokevirtual 165	java/io/File:isFile	()Z
    //   311: ifeq +52 -> 363
    //   314: aload 11
    //   316: invokevirtual 165	java/io/File:isFile	()Z
    //   319: ifeq +44 -> 363
    //   322: aload 10
    //   324: invokevirtual 178	java/io/File:length	()J
    //   327: l2i
    //   328: istore 63
    //   330: new 73	java/lang/StringBuilder
    //   333: dup
    //   334: ldc 180
    //   336: invokespecial 76	java/lang/StringBuilder:<init>	(Ljava/lang/String;)V
    //   339: aload_1
    //   340: invokevirtual 84	java/lang/StringBuilder:append	(Ljava/lang/String;)Ljava/lang/StringBuilder;
    //   343: invokevirtual 87	java/lang/StringBuilder:toString	()Ljava/lang/String;
    //   346: invokestatic 182	com/google/android/gms/b/hc:a	(Ljava/lang/String;)V
    //   349: aload_0
    //   350: aload_1
    //   351: aload 10
    //   353: invokevirtual 80	java/io/File:getAbsolutePath	()Ljava/lang/String;
    //   356: iload 63
    //   358: invokevirtual 185	com/google/android/gms/b/cw:a	(Ljava/lang/String;Ljava/lang/String;I)V
    //   361: iconst_1
    //   362: ireturn
    //   363: new 73	java/lang/StringBuilder
    //   366: dup
    //   367: invokespecial 98	java/lang/StringBuilder:<init>	()V
    //   370: aload_0
    //   371: getfield 64	com/google/android/gms/b/cw:d	Ljava/io/File;
    //   374: invokevirtual 80	java/io/File:getAbsolutePath	()Ljava/lang/String;
    //   377: invokevirtual 84	java/lang/StringBuilder:append	(Ljava/lang/String;)Ljava/lang/StringBuilder;
    //   380: aload_1
    //   381: invokevirtual 84	java/lang/StringBuilder:append	(Ljava/lang/String;)Ljava/lang/StringBuilder;
    //   384: invokevirtual 87	java/lang/StringBuilder:toString	()Ljava/lang/String;
    //   387: astore 12
    //   389: getstatic 27	com/google/android/gms/b/cw:b	Ljava/util/Set;
    //   392: astore 13
    //   394: aload 13
    //   396: monitorenter
    //   397: getstatic 27	com/google/android/gms/b/cw:b	Ljava/util/Set;
    //   400: aload 12
    //   402: invokeinterface 191 2 0
    //   407: ifeq +48 -> 455
    //   410: new 73	java/lang/StringBuilder
    //   413: dup
    //   414: ldc 193
    //   416: invokespecial 76	java/lang/StringBuilder:<init>	(Ljava/lang/String;)V
    //   419: aload_1
    //   420: invokevirtual 84	java/lang/StringBuilder:append	(Ljava/lang/String;)Ljava/lang/StringBuilder;
    //   423: invokevirtual 87	java/lang/StringBuilder:toString	()Ljava/lang/String;
    //   426: invokestatic 55	com/google/android/gms/b/hc:d	(Ljava/lang/String;)V
    //   429: aload_0
    //   430: aload_1
    //   431: aload 10
    //   433: invokevirtual 80	java/io/File:getAbsolutePath	()Ljava/lang/String;
    //   436: ldc 195
    //   438: aconst_null
    //   439: invokevirtual 115	com/google/android/gms/b/cw:a	(Ljava/lang/String;Ljava/lang/String;Ljava/lang/String;Ljava/lang/String;)V
    //   442: aload 13
    //   444: monitorexit
    //   445: iconst_0
    //   446: ireturn
    //   447: astore 14
    //   449: aload 13
    //   451: monitorexit
    //   452: aload 14
    //   454: athrow
    //   455: getstatic 27	com/google/android/gms/b/cw:b	Ljava/util/Set;
    //   458: aload 12
    //   460: invokeinterface 198 2 0
    //   465: pop
    //   466: aload 13
    //   468: monitorexit
    //   469: aconst_null
    //   470: astore 16
    //   472: new 200	java/net/URL
    //   475: dup
    //   476: aload_1
    //   477: invokespecial 201	java/net/URL:<init>	(Ljava/lang/String;)V
    //   480: invokevirtual 205	java/net/URL:openConnection	()Ljava/net/URLConnection;
    //   483: astore 23
    //   485: getstatic 208	com/google/android/gms/b/aD:k	Lcom/google/android/gms/b/au;
    //   488: astore 24
    //   490: invokestatic 127	com/google/android/gms/ads/internal/P:n	()Lcom/google/android/gms/b/aB;
    //   493: aload 24
    //   495: invokevirtual 132	com/google/android/gms/b/aB:a	(Lcom/google/android/gms/b/au;)Ljava/lang/Object;
    //   498: checkcast 134	java/lang/Integer
    //   501: invokevirtual 138	java/lang/Integer:intValue	()I
    //   504: istore 25
    //   506: aload 23
    //   508: iload 25
    //   510: invokevirtual 214	java/net/URLConnection:setConnectTimeout	(I)V
    //   513: aload 23
    //   515: iload 25
    //   517: invokevirtual 217	java/net/URLConnection:setReadTimeout	(I)V
    //   520: aload 23
    //   522: instanceof 219
    //   525: ifeq +208 -> 733
    //   528: aload 23
    //   530: checkcast 219	java/net/HttpURLConnection
    //   533: invokevirtual 222	java/net/HttpURLConnection:getResponseCode	()I
    //   536: istore 61
    //   538: iload 61
    //   540: sipush 400
    //   543: if_icmplt +190 -> 733
    //   546: ldc 224
    //   548: astore 18
    //   550: new 73	java/lang/StringBuilder
    //   553: dup
    //   554: ldc 226
    //   556: invokespecial 76	java/lang/StringBuilder:<init>	(Ljava/lang/String;)V
    //   559: iload 61
    //   561: invokestatic 229	java/lang/Integer:toString	(I)Ljava/lang/String;
    //   564: invokevirtual 84	java/lang/StringBuilder:append	(Ljava/lang/String;)Ljava/lang/StringBuilder;
    //   567: invokevirtual 87	java/lang/StringBuilder:toString	()Ljava/lang/String;
    //   570: astore 62
    //   572: aload 62
    //   574: astore 19
    //   576: new 106	java/io/IOException
    //   579: dup
    //   580: new 73	java/lang/StringBuilder
    //   583: dup
    //   584: ldc 231
    //   586: invokespecial 76	java/lang/StringBuilder:<init>	(Ljava/lang/String;)V
    //   589: iload 61
    //   591: invokevirtual 234	java/lang/StringBuilder:append	(I)Ljava/lang/StringBuilder;
    //   594: ldc 236
    //   596: invokevirtual 84	java/lang/StringBuilder:append	(Ljava/lang/String;)Ljava/lang/StringBuilder;
    //   599: aload_1
    //   600: invokevirtual 84	java/lang/StringBuilder:append	(Ljava/lang/String;)Ljava/lang/StringBuilder;
    //   603: invokevirtual 87	java/lang/StringBuilder:toString	()Ljava/lang/String;
    //   606: invokespecial 237	java/io/IOException:<init>	(Ljava/lang/String;)V
    //   609: athrow
    //   610: astore 17
    //   612: aload 17
    //   614: instanceof 108
    //   617: ifeq +12 -> 629
    //   620: invokestatic 241	com/google/android/gms/ads/internal/P:h	()Lcom/google/android/gms/b/hn;
    //   623: aload 17
    //   625: iconst_1
    //   626: invokevirtual 246	com/google/android/gms/b/hn:a	(Ljava/lang/Throwable;Z)V
    //   629: aload 16
    //   631: invokevirtual 251	java/io/FileOutputStream:close	()V
    //   634: aload_0
    //   635: getfield 253	com/google/android/gms/b/cw:e	Z
    //   638: ifeq +785 -> 1423
    //   641: new 73	java/lang/StringBuilder
    //   644: dup
    //   645: ldc 255
    //   647: invokespecial 76	java/lang/StringBuilder:<init>	(Ljava/lang/String;)V
    //   650: aload_1
    //   651: invokevirtual 84	java/lang/StringBuilder:append	(Ljava/lang/String;)Ljava/lang/StringBuilder;
    //   654: ldc_w 257
    //   657: invokevirtual 84	java/lang/StringBuilder:append	(Ljava/lang/String;)Ljava/lang/StringBuilder;
    //   660: invokevirtual 87	java/lang/StringBuilder:toString	()Ljava/lang/String;
    //   663: invokestatic 259	com/google/android/gms/b/hc:c	(Ljava/lang/String;)V
    //   666: aload 10
    //   668: invokevirtual 262	java/io/File:exists	()Z
    //   671: ifeq +35 -> 706
    //   674: aload 10
    //   676: invokevirtual 160	java/io/File:delete	()Z
    //   679: ifne +27 -> 706
    //   682: new 73	java/lang/StringBuilder
    //   685: dup
    //   686: ldc_w 264
    //   689: invokespecial 76	java/lang/StringBuilder:<init>	(Ljava/lang/String;)V
    //   692: aload 10
    //   694: invokevirtual 80	java/io/File:getAbsolutePath	()Ljava/lang/String;
    //   697: invokevirtual 84	java/lang/StringBuilder:append	(Ljava/lang/String;)Ljava/lang/StringBuilder;
    //   700: invokevirtual 87	java/lang/StringBuilder:toString	()Ljava/lang/String;
    //   703: invokestatic 55	com/google/android/gms/b/hc:d	(Ljava/lang/String;)V
    //   706: aload_0
    //   707: aload_1
    //   708: aload 10
    //   710: invokevirtual 80	java/io/File:getAbsolutePath	()Ljava/lang/String;
    //   713: aload 18
    //   715: aload 19
    //   717: invokevirtual 115	com/google/android/gms/b/cw:a	(Ljava/lang/String;Ljava/lang/String;Ljava/lang/String;Ljava/lang/String;)V
    //   720: getstatic 27	com/google/android/gms/b/cw:b	Ljava/util/Set;
    //   723: aload 12
    //   725: invokeinterface 267 2 0
    //   730: pop
    //   731: iconst_0
    //   732: ireturn
    //   733: aload 23
    //   735: invokevirtual 270	java/net/URLConnection:getContentLength	()I
    //   738: istore 26
    //   740: iload 26
    //   742: ifge +50 -> 792
    //   745: new 73	java/lang/StringBuilder
    //   748: dup
    //   749: ldc_w 272
    //   752: invokespecial 76	java/lang/StringBuilder:<init>	(Ljava/lang/String;)V
    //   755: aload_1
    //   756: invokevirtual 84	java/lang/StringBuilder:append	(Ljava/lang/String;)Ljava/lang/StringBuilder;
    //   759: invokevirtual 87	java/lang/StringBuilder:toString	()Ljava/lang/String;
    //   762: invokestatic 55	com/google/android/gms/b/hc:d	(Ljava/lang/String;)V
    //   765: aload_0
    //   766: aload_1
    //   767: aload 10
    //   769: invokevirtual 80	java/io/File:getAbsolutePath	()Ljava/lang/String;
    //   772: ldc_w 274
    //   775: aconst_null
    //   776: invokevirtual 115	com/google/android/gms/b/cw:a	(Ljava/lang/String;Ljava/lang/String;Ljava/lang/String;Ljava/lang/String;)V
    //   779: getstatic 27	com/google/android/gms/b/cw:b	Ljava/util/Set;
    //   782: aload 12
    //   784: invokeinterface 267 2 0
    //   789: pop
    //   790: iconst_0
    //   791: ireturn
    //   792: getstatic 36	com/google/android/gms/b/cw:c	Ljava/text/DecimalFormat;
    //   795: iload 26
    //   797: i2l
    //   798: invokevirtual 278	java/text/DecimalFormat:format	(J)Ljava/lang/String;
    //   801: astore 28
    //   803: getstatic 280	com/google/android/gms/b/aD:h	Lcom/google/android/gms/b/au;
    //   806: astore 29
    //   808: invokestatic 127	com/google/android/gms/ads/internal/P:n	()Lcom/google/android/gms/b/aB;
    //   811: aload 29
    //   813: invokevirtual 132	com/google/android/gms/b/aB:a	(Lcom/google/android/gms/b/au;)Ljava/lang/Object;
    //   816: checkcast 134	java/lang/Integer
    //   819: invokevirtual 138	java/lang/Integer:intValue	()I
    //   822: istore 30
    //   824: iload 26
    //   826: iload 30
    //   828: if_icmple +82 -> 910
    //   831: new 73	java/lang/StringBuilder
    //   834: dup
    //   835: ldc_w 282
    //   838: invokespecial 76	java/lang/StringBuilder:<init>	(Ljava/lang/String;)V
    //   841: aload 28
    //   843: invokevirtual 84	java/lang/StringBuilder:append	(Ljava/lang/String;)Ljava/lang/StringBuilder;
    //   846: ldc_w 284
    //   849: invokevirtual 84	java/lang/StringBuilder:append	(Ljava/lang/String;)Ljava/lang/StringBuilder;
    //   852: aload_1
    //   853: invokevirtual 84	java/lang/StringBuilder:append	(Ljava/lang/String;)Ljava/lang/StringBuilder;
    //   856: invokevirtual 87	java/lang/StringBuilder:toString	()Ljava/lang/String;
    //   859: invokestatic 55	com/google/android/gms/b/hc:d	(Ljava/lang/String;)V
    //   862: new 73	java/lang/StringBuilder
    //   865: dup
    //   866: ldc_w 286
    //   869: invokespecial 76	java/lang/StringBuilder:<init>	(Ljava/lang/String;)V
    //   872: aload 28
    //   874: invokevirtual 84	java/lang/StringBuilder:append	(Ljava/lang/String;)Ljava/lang/StringBuilder;
    //   877: invokevirtual 87	java/lang/StringBuilder:toString	()Ljava/lang/String;
    //   880: astore 31
    //   882: aload_0
    //   883: aload_1
    //   884: aload 10
    //   886: invokevirtual 80	java/io/File:getAbsolutePath	()Ljava/lang/String;
    //   889: ldc_w 288
    //   892: aload 31
    //   894: invokevirtual 115	com/google/android/gms/b/cw:a	(Ljava/lang/String;Ljava/lang/String;Ljava/lang/String;Ljava/lang/String;)V
    //   897: getstatic 27	com/google/android/gms/b/cw:b	Ljava/util/Set;
    //   900: aload 12
    //   902: invokeinterface 267 2 0
    //   907: pop
    //   908: iconst_0
    //   909: ireturn
    //   910: new 73	java/lang/StringBuilder
    //   913: dup
    //   914: ldc_w 290
    //   917: invokespecial 76	java/lang/StringBuilder:<init>	(Ljava/lang/String;)V
    //   920: aload 28
    //   922: invokevirtual 84	java/lang/StringBuilder:append	(Ljava/lang/String;)Ljava/lang/StringBuilder;
    //   925: ldc_w 292
    //   928: invokevirtual 84	java/lang/StringBuilder:append	(Ljava/lang/String;)Ljava/lang/StringBuilder;
    //   931: aload_1
    //   932: invokevirtual 84	java/lang/StringBuilder:append	(Ljava/lang/String;)Ljava/lang/StringBuilder;
    //   935: invokevirtual 87	java/lang/StringBuilder:toString	()Ljava/lang/String;
    //   938: invokestatic 182	com/google/android/gms/b/hc:a	(Ljava/lang/String;)V
    //   941: aload 23
    //   943: invokevirtual 296	java/net/URLConnection:getInputStream	()Ljava/io/InputStream;
    //   946: invokestatic 302	java/nio/channels/Channels:newChannel	(Ljava/io/InputStream;)Ljava/nio/channels/ReadableByteChannel;
    //   949: astore 33
    //   951: new 248	java/io/FileOutputStream
    //   954: dup
    //   955: aload 10
    //   957: invokespecial 305	java/io/FileOutputStream:<init>	(Ljava/io/File;)V
    //   960: astore 34
    //   962: aload 34
    //   964: invokevirtual 309	java/io/FileOutputStream:getChannel	()Ljava/nio/channels/FileChannel;
    //   967: astore 35
    //   969: ldc_w 310
    //   972: invokestatic 316	java/nio/ByteBuffer:allocate	(I)Ljava/nio/ByteBuffer;
    //   975: astore 36
    //   977: invokestatic 320	com/google/android/gms/ads/internal/P:i	()Lcom/google/android/gms/b/ju;
    //   980: astore 37
    //   982: iconst_0
    //   983: istore 38
    //   985: aload 37
    //   987: invokeinterface 324 1 0
    //   992: lstore 39
    //   994: getstatic 327	com/google/android/gms/b/aD:j	Lcom/google/android/gms/b/au;
    //   997: astore 41
    //   999: invokestatic 127	com/google/android/gms/ads/internal/P:n	()Lcom/google/android/gms/b/aB;
    //   1002: aload 41
    //   1004: invokevirtual 132	com/google/android/gms/b/aB:a	(Lcom/google/android/gms/b/au;)Ljava/lang/Object;
    //   1007: checkcast 329	java/lang/Long
    //   1010: invokevirtual 332	java/lang/Long:longValue	()J
    //   1013: lstore 42
    //   1015: new 334	com/google/android/gms/b/hY
    //   1018: dup
    //   1019: lload 42
    //   1021: invokespecial 337	com/google/android/gms/b/hY:<init>	(J)V
    //   1024: astore 44
    //   1026: getstatic 339	com/google/android/gms/b/aD:i	Lcom/google/android/gms/b/au;
    //   1029: astore 45
    //   1031: invokestatic 127	com/google/android/gms/ads/internal/P:n	()Lcom/google/android/gms/b/aB;
    //   1034: aload 45
    //   1036: invokevirtual 132	com/google/android/gms/b/aB:a	(Lcom/google/android/gms/b/au;)Ljava/lang/Object;
    //   1039: checkcast 329	java/lang/Long
    //   1042: invokevirtual 332	java/lang/Long:longValue	()J
    //   1045: lstore 46
    //   1047: aload 33
    //   1049: aload 36
    //   1051: invokeinterface 345 2 0
    //   1056: istore 48
    //   1058: iload 48
    //   1060: iflt +245 -> 1305
    //   1063: iload 38
    //   1065: iload 48
    //   1067: iadd
    //   1068: istore 38
    //   1070: iload 38
    //   1072: iload 30
    //   1074: if_icmple +55 -> 1129
    //   1077: ldc_w 288
    //   1080: astore 18
    //   1082: new 73	java/lang/StringBuilder
    //   1085: dup
    //   1086: ldc_w 286
    //   1089: invokespecial 76	java/lang/StringBuilder:<init>	(Ljava/lang/String;)V
    //   1092: iload 38
    //   1094: invokestatic 229	java/lang/Integer:toString	(I)Ljava/lang/String;
    //   1097: invokevirtual 84	java/lang/StringBuilder:append	(Ljava/lang/String;)Ljava/lang/StringBuilder;
    //   1100: invokevirtual 87	java/lang/StringBuilder:toString	()Ljava/lang/String;
    //   1103: astore 60
    //   1105: aload 60
    //   1107: astore 19
    //   1109: new 106	java/io/IOException
    //   1112: dup
    //   1113: ldc_w 347
    //   1116: invokespecial 237	java/io/IOException:<init>	(Ljava/lang/String;)V
    //   1119: athrow
    //   1120: astore 17
    //   1122: aload 34
    //   1124: astore 16
    //   1126: goto -514 -> 612
    //   1129: aload 36
    //   1131: invokevirtual 351	java/nio/ByteBuffer:flip	()Ljava/nio/Buffer;
    //   1134: pop
    //   1135: aload 35
    //   1137: aload 36
    //   1139: invokevirtual 356	java/nio/channels/FileChannel:write	(Ljava/nio/ByteBuffer;)I
    //   1142: ifgt -7 -> 1135
    //   1145: aload 36
    //   1147: invokevirtual 359	java/nio/ByteBuffer:clear	()Ljava/nio/Buffer;
    //   1150: pop
    //   1151: aload 37
    //   1153: invokeinterface 324 1 0
    //   1158: lload 39
    //   1160: lsub
    //   1161: ldc2_w 360
    //   1164: lload 46
    //   1166: lmul
    //   1167: lcmp
    //   1168: ifle +61 -> 1229
    //   1171: ldc_w 363
    //   1174: astore 18
    //   1176: new 73	java/lang/StringBuilder
    //   1179: dup
    //   1180: ldc_w 365
    //   1183: invokespecial 76	java/lang/StringBuilder:<init>	(Ljava/lang/String;)V
    //   1186: lload 46
    //   1188: invokestatic 367	java/lang/Long:toString	(J)Ljava/lang/String;
    //   1191: invokevirtual 84	java/lang/StringBuilder:append	(Ljava/lang/String;)Ljava/lang/StringBuilder;
    //   1194: ldc_w 369
    //   1197: invokevirtual 84	java/lang/StringBuilder:append	(Ljava/lang/String;)Ljava/lang/StringBuilder;
    //   1200: invokevirtual 87	java/lang/StringBuilder:toString	()Ljava/lang/String;
    //   1203: astore 57
    //   1205: aload 57
    //   1207: astore 19
    //   1209: new 106	java/io/IOException
    //   1212: dup
    //   1213: ldc_w 371
    //   1216: invokespecial 237	java/io/IOException:<init>	(Ljava/lang/String;)V
    //   1219: athrow
    //   1220: astore 17
    //   1222: aload 34
    //   1224: astore 16
    //   1226: goto -614 -> 612
    //   1229: aload_0
    //   1230: getfield 253	com/google/android/gms/b/cw:e	Z
    //   1233: ifeq +31 -> 1264
    //   1236: ldc_w 373
    //   1239: astore 18
    //   1241: new 106	java/io/IOException
    //   1244: dup
    //   1245: ldc_w 375
    //   1248: invokespecial 237	java/io/IOException:<init>	(Ljava/lang/String;)V
    //   1251: athrow
    //   1252: astore 17
    //   1254: aload 34
    //   1256: astore 16
    //   1258: aconst_null
    //   1259: astore 19
    //   1261: goto -649 -> 612
    //   1264: aload 44
    //   1266: invokevirtual 377	com/google/android/gms/b/hY:a	()Z
    //   1269: ifeq -222 -> 1047
    //   1272: aload 10
    //   1274: invokevirtual 80	java/io/File:getAbsolutePath	()Ljava/lang/String;
    //   1277: astore 58
    //   1279: getstatic 380	com/google/android/gms/ads/internal/util/client/a:a	Landroid/os/Handler;
    //   1282: new 382	com/google/android/gms/b/cr
    //   1285: dup
    //   1286: aload_0
    //   1287: aload_1
    //   1288: aload 58
    //   1290: iload 38
    //   1292: iload 26
    //   1294: iconst_0
    //   1295: invokespecial 385	com/google/android/gms/b/cr:<init>	(Lcom/google/android/gms/b/cq;Ljava/lang/String;Ljava/lang/String;IIZ)V
    //   1298: invokevirtual 391	android/os/Handler:post	(Ljava/lang/Runnable;)Z
    //   1301: pop
    //   1302: goto -255 -> 1047
    //   1305: aload 34
    //   1307: invokevirtual 251	java/io/FileOutputStream:close	()V
    //   1310: iconst_3
    //   1311: invokestatic 394	com/google/android/gms/b/hc:a	(I)Z
    //   1314: ifeq +45 -> 1359
    //   1317: getstatic 36	com/google/android/gms/b/cw:c	Ljava/text/DecimalFormat;
    //   1320: iload 38
    //   1322: i2l
    //   1323: invokevirtual 278	java/text/DecimalFormat:format	(J)Ljava/lang/String;
    //   1326: astore 54
    //   1328: new 73	java/lang/StringBuilder
    //   1331: dup
    //   1332: ldc_w 396
    //   1335: invokespecial 76	java/lang/StringBuilder:<init>	(Ljava/lang/String;)V
    //   1338: aload 54
    //   1340: invokevirtual 84	java/lang/StringBuilder:append	(Ljava/lang/String;)Ljava/lang/StringBuilder;
    //   1343: ldc_w 292
    //   1346: invokevirtual 84	java/lang/StringBuilder:append	(Ljava/lang/String;)Ljava/lang/StringBuilder;
    //   1349: aload_1
    //   1350: invokevirtual 84	java/lang/StringBuilder:append	(Ljava/lang/String;)Ljava/lang/StringBuilder;
    //   1353: invokevirtual 87	java/lang/StringBuilder:toString	()Ljava/lang/String;
    //   1356: invokestatic 182	com/google/android/gms/b/hc:a	(Ljava/lang/String;)V
    //   1359: aload 10
    //   1361: iconst_1
    //   1362: iconst_0
    //   1363: invokevirtual 91	java/io/File:setReadable	(ZZ)Z
    //   1366: pop
    //   1367: aload 11
    //   1369: invokevirtual 165	java/io/File:isFile	()Z
    //   1372: ifeq +37 -> 1409
    //   1375: aload 11
    //   1377: invokestatic 401	java/lang/System:currentTimeMillis	()J
    //   1380: invokevirtual 405	java/io/File:setLastModified	(J)Z
    //   1383: pop
    //   1384: aload_0
    //   1385: aload_1
    //   1386: aload 10
    //   1388: invokevirtual 80	java/io/File:getAbsolutePath	()Ljava/lang/String;
    //   1391: iload 38
    //   1393: invokevirtual 185	com/google/android/gms/b/cw:a	(Ljava/lang/String;Ljava/lang/String;I)V
    //   1396: getstatic 27	com/google/android/gms/b/cw:b	Ljava/util/Set;
    //   1399: aload 12
    //   1401: invokeinterface 267 2 0
    //   1406: pop
    //   1407: iconst_1
    //   1408: ireturn
    //   1409: aload 11
    //   1411: invokevirtual 408	java/io/File:createNewFile	()Z
    //   1414: pop
    //   1415: goto -31 -> 1384
    //   1418: astore 50
    //   1420: goto -36 -> 1384
    //   1423: new 73	java/lang/StringBuilder
    //   1426: dup
    //   1427: ldc_w 410
    //   1430: invokespecial 76	java/lang/StringBuilder:<init>	(Ljava/lang/String;)V
    //   1433: aload_1
    //   1434: invokevirtual 84	java/lang/StringBuilder:append	(Ljava/lang/String;)Ljava/lang/StringBuilder;
    //   1437: ldc_w 257
    //   1440: invokevirtual 84	java/lang/StringBuilder:append	(Ljava/lang/String;)Ljava/lang/StringBuilder;
    //   1443: invokevirtual 87	java/lang/StringBuilder:toString	()Ljava/lang/String;
    //   1446: aload 17
    //   1448: invokestatic 413	com/google/android/gms/b/hc:c	(Ljava/lang/String;Ljava/lang/Throwable;)V
    //   1451: goto -785 -> 666
    //   1454: astore 22
    //   1456: goto -822 -> 634
    //   1459: astore 20
    //   1461: goto -827 -> 634
    //   1464: astore 17
    //   1466: ldc_w 415
    //   1469: astore 18
    //   1471: aconst_null
    //   1472: astore 19
    //   1474: aconst_null
    //   1475: astore 16
    //   1477: goto -865 -> 612
    //   1480: astore 17
    //   1482: aconst_null
    //   1483: astore 19
    //   1485: aconst_null
    //   1486: astore 16
    //   1488: goto -876 -> 612
    //   1491: astore 17
    //   1493: aconst_null
    //   1494: astore 16
    //   1496: goto -884 -> 612
    //   1499: astore 17
    //   1501: ldc_w 415
    //   1504: astore 18
    //   1506: aload 34
    //   1508: astore 16
    //   1510: aconst_null
    //   1511: astore 19
    //   1513: goto -901 -> 612
    //   1516: astore 17
    //   1518: aload 34
    //   1520: astore 16
    //   1522: aconst_null
    //   1523: astore 19
    //   1525: goto -913 -> 612
    //   1528: astore 17
    //   1530: ldc_w 415
    //   1533: astore 18
    //   1535: aconst_null
    //   1536: astore 19
    //   1538: aconst_null
    //   1539: astore 16
    //   1541: goto -929 -> 612
    //   1544: astore 17
    //   1546: aconst_null
    //   1547: astore 19
    //   1549: aconst_null
    //   1550: astore 16
    //   1552: goto -940 -> 612
    //   1555: lload 65
    //   1557: lstore 73
    //   1559: aload 64
    //   1561: astore 75
    //   1563: goto -1355 -> 208
    //   1566: astore 17
    //   1568: ldc_w 415
    //   1571: astore 18
    //   1573: aload 34
    //   1575: astore 16
    //   1577: aconst_null
    //   1578: astore 19
    //   1580: goto -968 -> 612
    //
    // Exception table:
    //   from	to	target	type
    //   397	445	447	finally
    //   449	452	447	finally
    //   455	469	447	finally
    //   576	610	610	java/io/IOException
    //   1109	1120	1120	java/io/IOException
    //   1209	1220	1120	java/io/IOException
    //   1109	1120	1220	java/lang/RuntimeException
    //   1209	1220	1220	java/lang/RuntimeException
    //   1082	1105	1252	java/io/IOException
    //   1176	1205	1252	java/io/IOException
    //   1241	1252	1252	java/io/IOException
    //   1409	1415	1418	java/io/IOException
    //   629	634	1454	java/io/IOException
    //   629	634	1459	java/lang/NullPointerException
    //   472	538	1464	java/lang/RuntimeException
    //   733	740	1464	java/lang/RuntimeException
    //   745	790	1464	java/lang/RuntimeException
    //   792	824	1464	java/lang/RuntimeException
    //   831	908	1464	java/lang/RuntimeException
    //   910	962	1464	java/lang/RuntimeException
    //   550	572	1480	java/lang/RuntimeException
    //   576	610	1491	java/lang/RuntimeException
    //   962	982	1499	java/lang/RuntimeException
    //   985	1047	1499	java/lang/RuntimeException
    //   1047	1058	1499	java/lang/RuntimeException
    //   1129	1135	1499	java/lang/RuntimeException
    //   1135	1171	1499	java/lang/RuntimeException
    //   1229	1236	1499	java/lang/RuntimeException
    //   1264	1302	1499	java/lang/RuntimeException
    //   1305	1359	1499	java/lang/RuntimeException
    //   1359	1384	1499	java/lang/RuntimeException
    //   1384	1407	1499	java/lang/RuntimeException
    //   1409	1415	1499	java/lang/RuntimeException
    //   1082	1105	1516	java/lang/RuntimeException
    //   1176	1205	1516	java/lang/RuntimeException
    //   1241	1252	1516	java/lang/RuntimeException
    //   472	538	1528	java/io/IOException
    //   733	740	1528	java/io/IOException
    //   745	790	1528	java/io/IOException
    //   792	824	1528	java/io/IOException
    //   831	908	1528	java/io/IOException
    //   910	962	1528	java/io/IOException
    //   550	572	1544	java/io/IOException
    //   962	982	1566	java/io/IOException
    //   985	1047	1566	java/io/IOException
    //   1047	1058	1566	java/io/IOException
    //   1129	1135	1566	java/io/IOException
    //   1135	1171	1566	java/io/IOException
    //   1229	1236	1566	java/io/IOException
    //   1264	1302	1566	java/io/IOException
    //   1305	1359	1566	java/io/IOException
    //   1359	1384	1566	java/io/IOException
    //   1384	1407	1566	java/io/IOException
  }

  public final void b()
  {
    this.e = true;
  }
}

/* Location:           C:\Users\KSHITIZ GUPTA\Downloads\apktool-install-windws\dex2jar-0.0.9.15\dex2jar-0.0.9.15\classes_dex2jar.jar
 * Qualified Name:     com.google.android.gms.b.cw
 * JD-Core Version:    0.6.0
 */