package com.google.android.gms.b;

import java.util.concurrent.BlockingQueue;

public final class fl extends Thread
{
  private final BlockingQueue a;
  private final eu b;
  private final T c;
  private final jx d;
  private volatile boolean e = false;

  public fl(BlockingQueue paramBlockingQueue, eu parameu, T paramT, jx paramjx)
  {
    this.a = paramBlockingQueue;
    this.b = parameu;
    this.c = paramT;
    this.d = paramjx;
  }

  public final void a()
  {
    this.e = true;
    interrupt();
  }

  // ERROR //
  public final void run()
  {
    // Byte code:
    //   0: bipush 10
    //   2: invokestatic 45	android/os/Process:setThreadPriority	(I)V
    //   5: invokestatic 51	android/os/SystemClock:elapsedRealtime	()J
    //   8: pop2
    //   9: aload_0
    //   10: getfield 23	com/google/android/gms/b/fl:a	Ljava/util/concurrent/BlockingQueue;
    //   13: invokeinterface 57 1 0
    //   18: checkcast 59	com/google/android/gms/b/iR
    //   21: astore 4
    //   23: aload 4
    //   25: ldc 61
    //   27: invokevirtual 64	com/google/android/gms/b/iR:a	(Ljava/lang/String;)V
    //   30: getstatic 70	android/os/Build$VERSION:SDK_INT	I
    //   33: bipush 14
    //   35: if_icmplt +11 -> 46
    //   38: aload 4
    //   40: invokevirtual 73	com/google/android/gms/b/iR:c	()I
    //   43: invokestatic 78	android/net/TrafficStats:setThreadStatsTag	(I)V
    //   46: aload_0
    //   47: getfield 25	com/google/android/gms/b/fl:b	Lcom/google/android/gms/b/eu;
    //   50: aload 4
    //   52: invokeinterface 83 2 0
    //   57: astore 14
    //   59: aload 4
    //   61: ldc 85
    //   63: invokevirtual 64	com/google/android/gms/b/iR:a	(Ljava/lang/String;)V
    //   66: aload 14
    //   68: getfield 89	com/google/android/gms/b/gP:c	Z
    //   71: ifeq +57 -> 128
    //   74: aload 4
    //   76: invokevirtual 93	com/google/android/gms/b/iR:n	()Z
    //   79: ifeq +49 -> 128
    //   82: aload 4
    //   84: ldc 95
    //   86: invokevirtual 97	com/google/android/gms/b/iR:b	(Ljava/lang/String;)V
    //   89: goto -84 -> 5
    //   92: astore 10
    //   94: invokestatic 51	android/os/SystemClock:elapsedRealtime	()J
    //   97: pop2
    //   98: aload 10
    //   100: invokestatic 100	com/google/android/gms/b/iR:a	(Lcom/google/android/gms/b/kb;)Lcom/google/android/gms/b/kb;
    //   103: astore 13
    //   105: aload_0
    //   106: getfield 29	com/google/android/gms/b/fl:d	Lcom/google/android/gms/b/jx;
    //   109: aload 4
    //   111: aload 13
    //   113: invokevirtual 105	com/google/android/gms/b/jx:a	(Lcom/google/android/gms/b/iR;Lcom/google/android/gms/b/kb;)V
    //   116: goto -111 -> 5
    //   119: astore_3
    //   120: aload_0
    //   121: getfield 21	com/google/android/gms/b/fl:e	Z
    //   124: ifeq -119 -> 5
    //   127: return
    //   128: aload 4
    //   130: aload 14
    //   132: invokevirtual 108	com/google/android/gms/b/iR:a	(Lcom/google/android/gms/b/gP;)Lcom/google/android/gms/b/jq;
    //   135: astore 15
    //   137: aload 4
    //   139: ldc 110
    //   141: invokevirtual 64	com/google/android/gms/b/iR:a	(Ljava/lang/String;)V
    //   144: aload 4
    //   146: invokevirtual 113	com/google/android/gms/b/iR:j	()Z
    //   149: ifeq +37 -> 186
    //   152: aload 15
    //   154: getfield 118	com/google/android/gms/b/jq:b	Lcom/google/android/gms/b/U;
    //   157: ifnull +29 -> 186
    //   160: aload_0
    //   161: getfield 27	com/google/android/gms/b/fl:c	Lcom/google/android/gms/b/T;
    //   164: aload 4
    //   166: invokevirtual 121	com/google/android/gms/b/iR:e	()Ljava/lang/String;
    //   169: aload 15
    //   171: getfield 118	com/google/android/gms/b/jq:b	Lcom/google/android/gms/b/U;
    //   174: invokeinterface 126 3 0
    //   179: aload 4
    //   181: ldc 128
    //   183: invokevirtual 64	com/google/android/gms/b/iR:a	(Ljava/lang/String;)V
    //   186: aload 4
    //   188: invokevirtual 131	com/google/android/gms/b/iR:m	()V
    //   191: aload_0
    //   192: getfield 29	com/google/android/gms/b/fl:d	Lcom/google/android/gms/b/jx;
    //   195: aload 4
    //   197: aload 15
    //   199: invokevirtual 134	com/google/android/gms/b/jx:a	(Lcom/google/android/gms/b/iR;Lcom/google/android/gms/b/jq;)V
    //   202: goto -197 -> 5
    //   205: astore 5
    //   207: iconst_1
    //   208: anewarray 136	java/lang/Object
    //   211: astore 6
    //   213: aload 6
    //   215: iconst_0
    //   216: aload 5
    //   218: invokevirtual 139	java/lang/Exception:toString	()Ljava/lang/String;
    //   221: aastore
    //   222: aload 5
    //   224: ldc 141
    //   226: aload 6
    //   228: invokestatic 146	com/google/android/gms/b/kj:a	(Ljava/lang/Throwable;Ljava/lang/String;[Ljava/lang/Object;)V
    //   231: new 37	com/google/android/gms/b/kb
    //   234: dup
    //   235: aload 5
    //   237: invokespecial 149	com/google/android/gms/b/kb:<init>	(Ljava/lang/Throwable;)V
    //   240: astore 7
    //   242: invokestatic 51	android/os/SystemClock:elapsedRealtime	()J
    //   245: pop2
    //   246: aload_0
    //   247: getfield 29	com/google/android/gms/b/fl:d	Lcom/google/android/gms/b/jx;
    //   250: aload 4
    //   252: aload 7
    //   254: invokevirtual 105	com/google/android/gms/b/jx:a	(Lcom/google/android/gms/b/iR;Lcom/google/android/gms/b/kb;)V
    //   257: goto -252 -> 5
    //
    // Exception table:
    //   from	to	target	type
    //   23	46	92	com/google/android/gms/b/kb
    //   46	89	92	com/google/android/gms/b/kb
    //   128	186	92	com/google/android/gms/b/kb
    //   186	202	92	com/google/android/gms/b/kb
    //   9	23	119	java/lang/InterruptedException
    //   23	46	205	java/lang/Exception
    //   46	89	205	java/lang/Exception
    //   128	186	205	java/lang/Exception
    //   186	202	205	java/lang/Exception
  }
}

/* Location:           C:\Users\KSHITIZ GUPTA\Downloads\apktool-install-windws\dex2jar-0.0.9.15\dex2jar-0.0.9.15\classes_dex2jar.jar
 * Qualified Name:     com.google.android.gms.b.fl
 * JD-Core Version:    0.6.0
 */