package com.google.android.gms.b;

import android.content.Context;
import android.util.DisplayMetrics;
import android.view.MotionEvent;
import com.google.ads.a.a.a;
import com.google.android.gms.clearcut.b;
import com.google.android.gms.clearcut.d;
import com.google.android.gms.common.api.g;
import com.google.android.gms.common.i;
import java.io.UnsupportedEncodingException;
import java.lang.reflect.InvocationTargetException;
import java.lang.reflect.Method;
import java.nio.ByteBuffer;
import java.util.ArrayList;
import java.util.Random;
import java.util.concurrent.TimeUnit;

public abstract class t extends s
{
  private static long A = 0L;
  private static B B;
  private static boolean C = false;
  private static b D = null;
  private static a E;
  private static Random F = new Random();
  private static i G = i.b();
  private static boolean H;
  private static boolean I = false;
  private static boolean J = false;
  private static boolean K = false;
  private static boolean L = false;
  private static boolean M = false;
  protected static int j;
  private static Method k;
  private static Method l;
  private static Method m;
  private static Method n;
  private static Method o;
  private static Method p;
  private static Method q;
  private static Method r;
  private static Method s;
  private static Method t;
  private static Method u;
  private static Method v;
  private static Method w;
  private static String x;
  private static String y;
  private static String z;

  protected t(Context paramContext, A paramA)
  {
    super(paramContext, paramA);
    a locala = new a();
    E = locala;
    locala.a = paramContext.getPackageName();
  }

  private static String a(Context paramContext, A paramA)
  {
    if (y != null)
      return y;
    if (n == null)
      throw new u();
    try
    {
      localByteBuffer = (ByteBuffer)n.invoke(null, new Object[] { paramContext });
      if (localByteBuffer == null)
        throw new u();
    }
    catch (IllegalAccessException localIllegalAccessException)
    {
      ByteBuffer localByteBuffer;
      throw new u(localIllegalAccessException);
      String str = paramA.a(localByteBuffer.array(), true);
      y = str;
      return str;
    }
    catch (InvocationTargetException localInvocationTargetException)
    {
    }
    throw new u(localInvocationTargetException);
  }

  private static String a(byte[] paramArrayOfByte, String paramString)
  {
    try
    {
      String str = new String(B.a(paramArrayOfByte, paramString), "UTF-8");
      return str;
    }
    catch (C localC)
    {
      throw new u(localC);
    }
    catch (UnsupportedEncodingException localUnsupportedEncodingException)
    {
    }
    throw new u(localUnsupportedEncodingException);
  }

  private static ArrayList a(MotionEvent paramMotionEvent, DisplayMetrics paramDisplayMetrics)
  {
    if ((o == null) || (paramMotionEvent == null))
      throw new u();
    try
    {
      ArrayList localArrayList = (ArrayList)o.invoke(null, new Object[] { paramMotionEvent, paramDisplayMetrics });
      return localArrayList;
    }
    catch (IllegalAccessException localIllegalAccessException)
    {
      throw new u(localIllegalAccessException);
    }
    catch (InvocationTargetException localInvocationTargetException)
    {
    }
    throw new u(localInvocationTargetException);
  }

  protected static void a(int paramInt1, int paramInt2)
  {
    if ((L) && (I) && (D != null))
    {
      d locald = D.a(ku.a(E));
      locald.b(paramInt2);
      locald.a(paramInt1);
      locald.a(i);
    }
  }

  // ERROR //
  protected static void a(String paramString, Context paramContext, A paramA)
  {
    // Byte code:
    //   0: ldc 2
    //   2: monitorenter
    //   3: getstatic 48	com/google/android/gms/b/t:C	Z
    //   6: istore 4
    //   8: iload 4
    //   10: ifne +92 -> 102
    //   13: new 137	com/google/android/gms/b/B
    //   16: dup
    //   17: aload_2
    //   18: aconst_null
    //   19: invokespecial 193	com/google/android/gms/b/B:<init>	(Lcom/google/android/gms/b/A;Ljava/security/SecureRandom;)V
    //   22: putstatic 135	com/google/android/gms/b/t:B	Lcom/google/android/gms/b/B;
    //   25: aload_0
    //   26: putstatic 195	com/google/android/gms/b/t:x	Ljava/lang/String;
    //   29: aload_1
    //   30: invokestatic 200	com/google/android/gms/b/aD:a	(Landroid/content/Context;)V
    //   33: getstatic 135	com/google/android/gms/b/t:B	Lcom/google/android/gms/b/B;
    //   36: ldc 202
    //   38: invokevirtual 205	com/google/android/gms/b/B:a	(Ljava/lang/String;)[B
    //   41: astore 13
    //   43: getstatic 135	com/google/android/gms/b/t:B	Lcom/google/android/gms/b/B;
    //   46: aload 13
    //   48: ldc 207
    //   50: invokevirtual 140	com/google/android/gms/b/B:a	([BLjava/lang/String;)[B
    //   53: astore 14
    //   55: aload_1
    //   56: invokevirtual 211	android/content/Context:getCacheDir	()Ljava/io/File;
    //   59: astore 15
    //   61: aload 15
    //   63: ifnonnull +43 -> 106
    //   66: aload_1
    //   67: ldc 213
    //   69: iconst_0
    //   70: invokevirtual 217	android/content/Context:getDir	(Ljava/lang/String;I)Ljava/io/File;
    //   73: astore 15
    //   75: aload 15
    //   77: ifnonnull +29 -> 106
    //   80: new 103	com/google/android/gms/b/u
    //   83: dup
    //   84: invokespecial 104	com/google/android/gms/b/u:<init>	()V
    //   87: athrow
    //   88: astore 12
    //   90: new 103	com/google/android/gms/b/u
    //   93: dup
    //   94: aload 12
    //   96: invokespecial 117	com/google/android/gms/b/u:<init>	(Ljava/lang/Throwable;)V
    //   99: athrow
    //   100: astore 6
    //   102: ldc 2
    //   104: monitorexit
    //   105: return
    //   106: aload 15
    //   108: astore 16
    //   110: ldc 219
    //   112: ldc 221
    //   114: aload 16
    //   116: invokestatic 227	java/io/File:createTempFile	(Ljava/lang/String;Ljava/lang/String;Ljava/io/File;)Ljava/io/File;
    //   119: astore 17
    //   121: new 229	java/io/FileOutputStream
    //   124: dup
    //   125: aload 17
    //   127: invokespecial 232	java/io/FileOutputStream:<init>	(Ljava/io/File;)V
    //   130: astore 18
    //   132: aload 18
    //   134: aload 14
    //   136: iconst_0
    //   137: aload 14
    //   139: arraylength
    //   140: invokevirtual 236	java/io/FileOutputStream:write	([BII)V
    //   143: aload 18
    //   145: invokevirtual 239	java/io/FileOutputStream:close	()V
    //   148: new 241	dalvik/system/DexClassLoader
    //   151: dup
    //   152: aload 17
    //   154: invokevirtual 244	java/io/File:getAbsolutePath	()Ljava/lang/String;
    //   157: aload 16
    //   159: invokevirtual 244	java/io/File:getAbsolutePath	()Ljava/lang/String;
    //   162: aconst_null
    //   163: aload_1
    //   164: invokevirtual 248	android/content/Context:getClassLoader	()Ljava/lang/ClassLoader;
    //   167: invokespecial 251	dalvik/system/DexClassLoader:<init>	(Ljava/lang/String;Ljava/lang/String;Ljava/lang/String;Ljava/lang/ClassLoader;)V
    //   170: astore 19
    //   172: aload 19
    //   174: aload 13
    //   176: ldc 253
    //   178: invokestatic 255	com/google/android/gms/b/t:a	([BLjava/lang/String;)Ljava/lang/String;
    //   181: invokevirtual 259	dalvik/system/DexClassLoader:loadClass	(Ljava/lang/String;)Ljava/lang/Class;
    //   184: astore 24
    //   186: aload 19
    //   188: aload 13
    //   190: ldc_w 261
    //   193: invokestatic 255	com/google/android/gms/b/t:a	([BLjava/lang/String;)Ljava/lang/String;
    //   196: invokevirtual 259	dalvik/system/DexClassLoader:loadClass	(Ljava/lang/String;)Ljava/lang/Class;
    //   199: astore 25
    //   201: aload 19
    //   203: aload 13
    //   205: ldc_w 263
    //   208: invokestatic 255	com/google/android/gms/b/t:a	([BLjava/lang/String;)Ljava/lang/String;
    //   211: invokevirtual 259	dalvik/system/DexClassLoader:loadClass	(Ljava/lang/String;)Ljava/lang/Class;
    //   214: astore 26
    //   216: aload 19
    //   218: aload 13
    //   220: ldc_w 265
    //   223: invokestatic 255	com/google/android/gms/b/t:a	([BLjava/lang/String;)Ljava/lang/String;
    //   226: invokevirtual 259	dalvik/system/DexClassLoader:loadClass	(Ljava/lang/String;)Ljava/lang/Class;
    //   229: astore 27
    //   231: aload 19
    //   233: aload 13
    //   235: ldc_w 267
    //   238: invokestatic 255	com/google/android/gms/b/t:a	([BLjava/lang/String;)Ljava/lang/String;
    //   241: invokevirtual 259	dalvik/system/DexClassLoader:loadClass	(Ljava/lang/String;)Ljava/lang/Class;
    //   244: astore 28
    //   246: aload 19
    //   248: aload 13
    //   250: ldc_w 269
    //   253: invokestatic 255	com/google/android/gms/b/t:a	([BLjava/lang/String;)Ljava/lang/String;
    //   256: invokevirtual 259	dalvik/system/DexClassLoader:loadClass	(Ljava/lang/String;)Ljava/lang/Class;
    //   259: astore 29
    //   261: aload 19
    //   263: aload 13
    //   265: ldc_w 271
    //   268: invokestatic 255	com/google/android/gms/b/t:a	([BLjava/lang/String;)Ljava/lang/String;
    //   271: invokevirtual 259	dalvik/system/DexClassLoader:loadClass	(Ljava/lang/String;)Ljava/lang/Class;
    //   274: astore 30
    //   276: aload 19
    //   278: aload 13
    //   280: ldc_w 273
    //   283: invokestatic 255	com/google/android/gms/b/t:a	([BLjava/lang/String;)Ljava/lang/String;
    //   286: invokevirtual 259	dalvik/system/DexClassLoader:loadClass	(Ljava/lang/String;)Ljava/lang/Class;
    //   289: astore 31
    //   291: aload 19
    //   293: aload 13
    //   295: ldc_w 275
    //   298: invokestatic 255	com/google/android/gms/b/t:a	([BLjava/lang/String;)Ljava/lang/String;
    //   301: invokevirtual 259	dalvik/system/DexClassLoader:loadClass	(Ljava/lang/String;)Ljava/lang/Class;
    //   304: astore 32
    //   306: aload 19
    //   308: aload 13
    //   310: ldc_w 277
    //   313: invokestatic 255	com/google/android/gms/b/t:a	([BLjava/lang/String;)Ljava/lang/String;
    //   316: invokevirtual 259	dalvik/system/DexClassLoader:loadClass	(Ljava/lang/String;)Ljava/lang/Class;
    //   319: astore 33
    //   321: aload 19
    //   323: aload 13
    //   325: ldc_w 279
    //   328: invokestatic 255	com/google/android/gms/b/t:a	([BLjava/lang/String;)Ljava/lang/String;
    //   331: invokevirtual 259	dalvik/system/DexClassLoader:loadClass	(Ljava/lang/String;)Ljava/lang/Class;
    //   334: astore 34
    //   336: aload 19
    //   338: aload 13
    //   340: ldc_w 281
    //   343: invokestatic 255	com/google/android/gms/b/t:a	([BLjava/lang/String;)Ljava/lang/String;
    //   346: invokevirtual 259	dalvik/system/DexClassLoader:loadClass	(Ljava/lang/String;)Ljava/lang/Class;
    //   349: astore 35
    //   351: aload 19
    //   353: aload 13
    //   355: ldc_w 283
    //   358: invokestatic 255	com/google/android/gms/b/t:a	([BLjava/lang/String;)Ljava/lang/String;
    //   361: invokevirtual 259	dalvik/system/DexClassLoader:loadClass	(Ljava/lang/String;)Ljava/lang/Class;
    //   364: astore 36
    //   366: aload 24
    //   368: aload 13
    //   370: ldc_w 285
    //   373: invokestatic 255	com/google/android/gms/b/t:a	([BLjava/lang/String;)Ljava/lang/String;
    //   376: iconst_0
    //   377: anewarray 287	java/lang/Class
    //   380: invokevirtual 291	java/lang/Class:getMethod	(Ljava/lang/String;[Ljava/lang/Class;)Ljava/lang/reflect/Method;
    //   383: putstatic 293	com/google/android/gms/b/t:k	Ljava/lang/reflect/Method;
    //   386: aload 25
    //   388: aload 13
    //   390: ldc_w 295
    //   393: invokestatic 255	com/google/android/gms/b/t:a	([BLjava/lang/String;)Ljava/lang/String;
    //   396: iconst_0
    //   397: anewarray 287	java/lang/Class
    //   400: invokevirtual 291	java/lang/Class:getMethod	(Ljava/lang/String;[Ljava/lang/Class;)Ljava/lang/reflect/Method;
    //   403: putstatic 297	com/google/android/gms/b/t:l	Ljava/lang/reflect/Method;
    //   406: aload 26
    //   408: aload 13
    //   410: ldc_w 299
    //   413: invokestatic 255	com/google/android/gms/b/t:a	([BLjava/lang/String;)Ljava/lang/String;
    //   416: iconst_0
    //   417: anewarray 287	java/lang/Class
    //   420: invokevirtual 291	java/lang/Class:getMethod	(Ljava/lang/String;[Ljava/lang/Class;)Ljava/lang/reflect/Method;
    //   423: putstatic 301	com/google/android/gms/b/t:m	Ljava/lang/reflect/Method;
    //   426: aload 27
    //   428: aload 13
    //   430: ldc_w 303
    //   433: invokestatic 255	com/google/android/gms/b/t:a	([BLjava/lang/String;)Ljava/lang/String;
    //   436: iconst_1
    //   437: anewarray 287	java/lang/Class
    //   440: dup
    //   441: iconst_0
    //   442: ldc 85
    //   444: aastore
    //   445: invokevirtual 291	java/lang/Class:getMethod	(Ljava/lang/String;[Ljava/lang/Class;)Ljava/lang/reflect/Method;
    //   448: putstatic 101	com/google/android/gms/b/t:n	Ljava/lang/reflect/Method;
    //   451: aload 28
    //   453: aload 13
    //   455: ldc_w 305
    //   458: invokestatic 255	com/google/android/gms/b/t:a	([BLjava/lang/String;)Ljava/lang/String;
    //   461: iconst_2
    //   462: anewarray 287	java/lang/Class
    //   465: dup
    //   466: iconst_0
    //   467: ldc_w 307
    //   470: aastore
    //   471: dup
    //   472: iconst_1
    //   473: ldc_w 309
    //   476: aastore
    //   477: invokevirtual 291	java/lang/Class:getMethod	(Ljava/lang/String;[Ljava/lang/Class;)Ljava/lang/reflect/Method;
    //   480: putstatic 148	com/google/android/gms/b/t:o	Ljava/lang/reflect/Method;
    //   483: aload 29
    //   485: aload 13
    //   487: ldc_w 311
    //   490: invokestatic 255	com/google/android/gms/b/t:a	([BLjava/lang/String;)Ljava/lang/String;
    //   493: iconst_1
    //   494: anewarray 287	java/lang/Class
    //   497: dup
    //   498: iconst_0
    //   499: ldc 85
    //   501: aastore
    //   502: invokevirtual 291	java/lang/Class:getMethod	(Ljava/lang/String;[Ljava/lang/Class;)Ljava/lang/reflect/Method;
    //   505: putstatic 313	com/google/android/gms/b/t:p	Ljava/lang/reflect/Method;
    //   508: aload 30
    //   510: aload 13
    //   512: ldc_w 315
    //   515: invokestatic 255	com/google/android/gms/b/t:a	([BLjava/lang/String;)Ljava/lang/String;
    //   518: iconst_1
    //   519: anewarray 287	java/lang/Class
    //   522: dup
    //   523: iconst_0
    //   524: ldc 85
    //   526: aastore
    //   527: invokevirtual 291	java/lang/Class:getMethod	(Ljava/lang/String;[Ljava/lang/Class;)Ljava/lang/reflect/Method;
    //   530: putstatic 317	com/google/android/gms/b/t:q	Ljava/lang/reflect/Method;
    //   533: aload 31
    //   535: aload 13
    //   537: ldc_w 319
    //   540: invokestatic 255	com/google/android/gms/b/t:a	([BLjava/lang/String;)Ljava/lang/String;
    //   543: iconst_1
    //   544: anewarray 287	java/lang/Class
    //   547: dup
    //   548: iconst_0
    //   549: ldc 85
    //   551: aastore
    //   552: invokevirtual 291	java/lang/Class:getMethod	(Ljava/lang/String;[Ljava/lang/Class;)Ljava/lang/reflect/Method;
    //   555: putstatic 321	com/google/android/gms/b/t:r	Ljava/lang/reflect/Method;
    //   558: aload 32
    //   560: aload 13
    //   562: ldc_w 323
    //   565: invokestatic 255	com/google/android/gms/b/t:a	([BLjava/lang/String;)Ljava/lang/String;
    //   568: iconst_1
    //   569: anewarray 287	java/lang/Class
    //   572: dup
    //   573: iconst_0
    //   574: ldc 85
    //   576: aastore
    //   577: invokevirtual 291	java/lang/Class:getMethod	(Ljava/lang/String;[Ljava/lang/Class;)Ljava/lang/reflect/Method;
    //   580: putstatic 325	com/google/android/gms/b/t:s	Ljava/lang/reflect/Method;
    //   583: aload 33
    //   585: aload 13
    //   587: ldc_w 327
    //   590: invokestatic 255	com/google/android/gms/b/t:a	([BLjava/lang/String;)Ljava/lang/String;
    //   593: iconst_1
    //   594: anewarray 287	java/lang/Class
    //   597: dup
    //   598: iconst_0
    //   599: ldc 85
    //   601: aastore
    //   602: invokevirtual 291	java/lang/Class:getMethod	(Ljava/lang/String;[Ljava/lang/Class;)Ljava/lang/reflect/Method;
    //   605: putstatic 329	com/google/android/gms/b/t:t	Ljava/lang/reflect/Method;
    //   608: aload 34
    //   610: aload 13
    //   612: ldc_w 331
    //   615: invokestatic 255	com/google/android/gms/b/t:a	([BLjava/lang/String;)Ljava/lang/String;
    //   618: iconst_1
    //   619: anewarray 287	java/lang/Class
    //   622: dup
    //   623: iconst_0
    //   624: ldc 85
    //   626: aastore
    //   627: invokevirtual 291	java/lang/Class:getMethod	(Ljava/lang/String;[Ljava/lang/Class;)Ljava/lang/reflect/Method;
    //   630: putstatic 333	com/google/android/gms/b/t:u	Ljava/lang/reflect/Method;
    //   633: aload 35
    //   635: aload 13
    //   637: ldc_w 335
    //   640: invokestatic 255	com/google/android/gms/b/t:a	([BLjava/lang/String;)Ljava/lang/String;
    //   643: iconst_1
    //   644: anewarray 287	java/lang/Class
    //   647: dup
    //   648: iconst_0
    //   649: ldc 85
    //   651: aastore
    //   652: invokevirtual 291	java/lang/Class:getMethod	(Ljava/lang/String;[Ljava/lang/Class;)Ljava/lang/reflect/Method;
    //   655: putstatic 337	com/google/android/gms/b/t:v	Ljava/lang/reflect/Method;
    //   658: aload 36
    //   660: aload 13
    //   662: ldc_w 339
    //   665: invokestatic 255	com/google/android/gms/b/t:a	([BLjava/lang/String;)Ljava/lang/String;
    //   668: iconst_1
    //   669: anewarray 287	java/lang/Class
    //   672: dup
    //   673: iconst_0
    //   674: ldc 85
    //   676: aastore
    //   677: invokevirtual 291	java/lang/Class:getMethod	(Ljava/lang/String;[Ljava/lang/Class;)Ljava/lang/reflect/Method;
    //   680: putstatic 341	com/google/android/gms/b/t:w	Ljava/lang/reflect/Method;
    //   683: aload 17
    //   685: invokevirtual 344	java/io/File:getName	()Ljava/lang/String;
    //   688: astore 37
    //   690: aload 17
    //   692: invokevirtual 348	java/io/File:delete	()Z
    //   695: pop
    //   696: new 223	java/io/File
    //   699: dup
    //   700: aload 16
    //   702: aload 37
    //   704: ldc 221
    //   706: ldc_w 350
    //   709: invokevirtual 354	java/lang/String:replace	(Ljava/lang/CharSequence;Ljava/lang/CharSequence;)Ljava/lang/String;
    //   712: invokespecial 357	java/io/File:<init>	(Ljava/io/File;Ljava/lang/String;)V
    //   715: invokevirtual 348	java/io/File:delete	()Z
    //   718: pop
    //   719: invokestatic 361	com/google/android/gms/b/t:e	()Ljava/lang/Long;
    //   722: invokevirtual 367	java/lang/Long:longValue	()J
    //   725: putstatic 46	com/google/android/gms/b/t:A	J
    //   728: new 52	java/util/Random
    //   731: dup
    //   732: invokespecial 55	java/util/Random:<init>	()V
    //   735: putstatic 57	com/google/android/gms/b/t:F	Ljava/util/Random;
    //   738: new 369	com/google/android/gms/common/api/h
    //   741: dup
    //   742: aload_1
    //   743: invokespecial 371	com/google/android/gms/common/api/h:<init>	(Landroid/content/Context;)V
    //   746: getstatic 374	com/google/android/gms/clearcut/b:b	Lcom/google/android/gms/common/api/a;
    //   749: invokevirtual 377	com/google/android/gms/common/api/h:a	(Lcom/google/android/gms/common/api/a;)Lcom/google/android/gms/common/api/h;
    //   752: invokevirtual 380	com/google/android/gms/common/api/h:b	()Lcom/google/android/gms/common/api/g;
    //   755: putstatic 172	com/google/android/gms/b/t:i	Lcom/google/android/gms/common/api/g;
    //   758: invokestatic 63	com/google/android/gms/common/i:b	()Lcom/google/android/gms/common/i;
    //   761: astore 42
    //   763: aload 42
    //   765: putstatic 65	com/google/android/gms/b/t:G	Lcom/google/android/gms/common/i;
    //   768: aload 42
    //   770: aload_1
    //   771: invokevirtual 383	com/google/android/gms/common/i:a	(Landroid/content/Context;)I
    //   774: ifne +190 -> 964
    //   777: iconst_1
    //   778: istore 43
    //   780: iload 43
    //   782: putstatic 385	com/google/android/gms/b/t:H	Z
    //   785: aload_1
    //   786: invokestatic 200	com/google/android/gms/b/aD:a	(Landroid/content/Context;)V
    //   789: getstatic 389	com/google/android/gms/b/aD:ab	Lcom/google/android/gms/b/au;
    //   792: astore 44
    //   794: invokestatic 394	com/google/android/gms/ads/internal/P:n	()Lcom/google/android/gms/b/aB;
    //   797: aload 44
    //   799: invokevirtual 399	com/google/android/gms/b/aB:a	(Lcom/google/android/gms/b/au;)Ljava/lang/Object;
    //   802: checkcast 401	java/lang/Boolean
    //   805: invokevirtual 404	java/lang/Boolean:booleanValue	()Z
    //   808: putstatic 67	com/google/android/gms/b/t:I	Z
    //   811: new 158	com/google/android/gms/clearcut/b
    //   814: dup
    //   815: aload_1
    //   816: ldc_w 406
    //   819: aconst_null
    //   820: aconst_null
    //   821: invokespecial 409	com/google/android/gms/clearcut/b:<init>	(Landroid/content/Context;Ljava/lang/String;Ljava/lang/String;Ljava/lang/String;)V
    //   824: putstatic 50	com/google/android/gms/b/t:D	Lcom/google/android/gms/clearcut/b;
    //   827: getstatic 65	com/google/android/gms/b/t:G	Lcom/google/android/gms/common/i;
    //   830: aload_1
    //   831: invokevirtual 411	com/google/android/gms/common/i:b	(Landroid/content/Context;)I
    //   834: ifle +136 -> 970
    //   837: iconst_1
    //   838: istore 41
    //   840: iload 41
    //   842: putstatic 75	com/google/android/gms/b/t:M	Z
    //   845: iconst_1
    //   846: putstatic 48	com/google/android/gms/b/t:C	Z
    //   849: goto -747 -> 102
    //   852: astore 5
    //   854: goto -752 -> 102
    //   857: astore 20
    //   859: aload 17
    //   861: invokevirtual 344	java/io/File:getName	()Ljava/lang/String;
    //   864: astore 21
    //   866: aload 17
    //   868: invokevirtual 348	java/io/File:delete	()Z
    //   871: pop
    //   872: new 223	java/io/File
    //   875: dup
    //   876: aload 16
    //   878: aload 21
    //   880: ldc 221
    //   882: ldc_w 350
    //   885: invokevirtual 354	java/lang/String:replace	(Ljava/lang/CharSequence;Ljava/lang/CharSequence;)Ljava/lang/String;
    //   888: invokespecial 357	java/io/File:<init>	(Ljava/io/File;Ljava/lang/String;)V
    //   891: invokevirtual 348	java/io/File:delete	()Z
    //   894: pop
    //   895: aload 20
    //   897: athrow
    //   898: astore 11
    //   900: new 103	com/google/android/gms/b/u
    //   903: dup
    //   904: aload 11
    //   906: invokespecial 117	com/google/android/gms/b/u:<init>	(Ljava/lang/Throwable;)V
    //   909: athrow
    //   910: astore_3
    //   911: ldc 2
    //   913: monitorexit
    //   914: aload_3
    //   915: athrow
    //   916: astore 10
    //   918: new 103	com/google/android/gms/b/u
    //   921: dup
    //   922: aload 10
    //   924: invokespecial 117	com/google/android/gms/b/u:<init>	(Ljava/lang/Throwable;)V
    //   927: athrow
    //   928: astore 9
    //   930: new 103	com/google/android/gms/b/u
    //   933: dup
    //   934: aload 9
    //   936: invokespecial 117	com/google/android/gms/b/u:<init>	(Ljava/lang/Throwable;)V
    //   939: athrow
    //   940: astore 8
    //   942: new 103	com/google/android/gms/b/u
    //   945: dup
    //   946: aload 8
    //   948: invokespecial 117	com/google/android/gms/b/u:<init>	(Ljava/lang/Throwable;)V
    //   951: athrow
    //   952: astore 7
    //   954: new 103	com/google/android/gms/b/u
    //   957: dup
    //   958: aload 7
    //   960: invokespecial 117	com/google/android/gms/b/u:<init>	(Ljava/lang/Throwable;)V
    //   963: athrow
    //   964: iconst_0
    //   965: istore 43
    //   967: goto -187 -> 780
    //   970: iconst_0
    //   971: istore 41
    //   973: goto -133 -> 840
    //   976: astore 40
    //   978: goto -151 -> 827
    //
    // Exception table:
    //   from	to	target	type
    //   33	61	88	java/io/FileNotFoundException
    //   66	75	88	java/io/FileNotFoundException
    //   80	88	88	java/io/FileNotFoundException
    //   110	148	88	java/io/FileNotFoundException
    //   683	719	88	java/io/FileNotFoundException
    //   859	898	88	java/io/FileNotFoundException
    //   13	33	100	com/google/android/gms/b/u
    //   33	61	100	com/google/android/gms/b/u
    //   66	75	100	com/google/android/gms/b/u
    //   80	88	100	com/google/android/gms/b/u
    //   90	100	100	com/google/android/gms/b/u
    //   110	148	100	com/google/android/gms/b/u
    //   683	719	100	com/google/android/gms/b/u
    //   719	738	100	com/google/android/gms/b/u
    //   738	777	100	com/google/android/gms/b/u
    //   780	827	100	com/google/android/gms/b/u
    //   827	837	100	com/google/android/gms/b/u
    //   840	849	100	com/google/android/gms/b/u
    //   859	898	100	com/google/android/gms/b/u
    //   900	910	100	com/google/android/gms/b/u
    //   918	928	100	com/google/android/gms/b/u
    //   930	940	100	com/google/android/gms/b/u
    //   942	952	100	com/google/android/gms/b/u
    //   954	964	100	com/google/android/gms/b/u
    //   13	33	852	java/lang/UnsupportedOperationException
    //   33	61	852	java/lang/UnsupportedOperationException
    //   66	75	852	java/lang/UnsupportedOperationException
    //   80	88	852	java/lang/UnsupportedOperationException
    //   90	100	852	java/lang/UnsupportedOperationException
    //   110	148	852	java/lang/UnsupportedOperationException
    //   683	719	852	java/lang/UnsupportedOperationException
    //   719	738	852	java/lang/UnsupportedOperationException
    //   738	777	852	java/lang/UnsupportedOperationException
    //   780	827	852	java/lang/UnsupportedOperationException
    //   827	837	852	java/lang/UnsupportedOperationException
    //   840	849	852	java/lang/UnsupportedOperationException
    //   859	898	852	java/lang/UnsupportedOperationException
    //   900	910	852	java/lang/UnsupportedOperationException
    //   918	928	852	java/lang/UnsupportedOperationException
    //   930	940	852	java/lang/UnsupportedOperationException
    //   942	952	852	java/lang/UnsupportedOperationException
    //   954	964	852	java/lang/UnsupportedOperationException
    //   148	683	857	finally
    //   33	61	898	java/io/IOException
    //   66	75	898	java/io/IOException
    //   80	88	898	java/io/IOException
    //   110	148	898	java/io/IOException
    //   683	719	898	java/io/IOException
    //   859	898	898	java/io/IOException
    //   3	8	910	finally
    //   13	33	910	finally
    //   33	61	910	finally
    //   66	75	910	finally
    //   80	88	910	finally
    //   90	100	910	finally
    //   110	148	910	finally
    //   683	719	910	finally
    //   719	738	910	finally
    //   738	777	910	finally
    //   780	827	910	finally
    //   827	837	910	finally
    //   840	849	910	finally
    //   859	898	910	finally
    //   900	910	910	finally
    //   918	928	910	finally
    //   930	940	910	finally
    //   942	952	910	finally
    //   954	964	910	finally
    //   33	61	916	java/lang/ClassNotFoundException
    //   66	75	916	java/lang/ClassNotFoundException
    //   80	88	916	java/lang/ClassNotFoundException
    //   110	148	916	java/lang/ClassNotFoundException
    //   683	719	916	java/lang/ClassNotFoundException
    //   859	898	916	java/lang/ClassNotFoundException
    //   33	61	928	com/google/android/gms/b/C
    //   66	75	928	com/google/android/gms/b/C
    //   80	88	928	com/google/android/gms/b/C
    //   110	148	928	com/google/android/gms/b/C
    //   683	719	928	com/google/android/gms/b/C
    //   859	898	928	com/google/android/gms/b/C
    //   33	61	940	java/lang/NoSuchMethodException
    //   66	75	940	java/lang/NoSuchMethodException
    //   80	88	940	java/lang/NoSuchMethodException
    //   110	148	940	java/lang/NoSuchMethodException
    //   683	719	940	java/lang/NoSuchMethodException
    //   859	898	940	java/lang/NoSuchMethodException
    //   33	61	952	java/lang/NullPointerException
    //   66	75	952	java/lang/NullPointerException
    //   80	88	952	java/lang/NullPointerException
    //   110	148	952	java/lang/NullPointerException
    //   683	719	952	java/lang/NullPointerException
    //   859	898	952	java/lang/NullPointerException
    //   738	777	976	java/lang/NoClassDefFoundError
    //   780	827	976	java/lang/NoClassDefFoundError
  }

  protected static boolean a()
  {
    return M;
  }

  private static String b(Context paramContext, A paramA)
  {
    if (z != null)
      return z;
    if (q == null)
      throw new u();
    try
    {
      localByteBuffer = (ByteBuffer)q.invoke(null, new Object[] { paramContext });
      if (localByteBuffer == null)
        throw new u();
    }
    catch (IllegalAccessException localIllegalAccessException)
    {
      ByteBuffer localByteBuffer;
      throw new u(localIllegalAccessException);
      String str = paramA.a(localByteBuffer.array(), true);
      z = str;
      return str;
    }
    catch (InvocationTargetException localInvocationTargetException)
    {
    }
    throw new u(localInvocationTargetException);
  }

  private static void b()
  {
    if (H)
    {
      i.b();
      L = true;
      return;
    }
    L = false;
  }

  private static void c()
  {
    if ((L) && (D != null))
    {
      D.a(i, 100L, TimeUnit.MILLISECONDS);
      i.c();
    }
  }

  private static String d()
  {
    if (x == null)
      throw new u();
    return x;
  }

  static String d(Context paramContext)
  {
    if (p == null)
      throw new u();
    String str;
    try
    {
      str = (String)p.invoke(null, new Object[] { paramContext });
      if (str == null)
        throw new u();
    }
    catch (IllegalAccessException localIllegalAccessException)
    {
      throw new u(localIllegalAccessException);
    }
    catch (InvocationTargetException localInvocationTargetException)
    {
      throw new u(localInvocationTargetException);
    }
    return str;
  }

  private static Long e()
  {
    if (k == null)
      throw new u();
    try
    {
      Long localLong = (Long)k.invoke(null, new Object[0]);
      return localLong;
    }
    catch (IllegalAccessException localIllegalAccessException)
    {
      throw new u(localIllegalAccessException);
    }
    catch (InvocationTargetException localInvocationTargetException)
    {
    }
    throw new u(localInvocationTargetException);
  }

  private static String e(Context paramContext)
  {
    if (t == null)
      throw new u();
    try
    {
      String str = (String)t.invoke(null, new Object[] { paramContext });
      return str;
    }
    catch (IllegalAccessException localIllegalAccessException)
    {
      throw new u(localIllegalAccessException);
    }
    catch (InvocationTargetException localInvocationTargetException)
    {
    }
    throw new u(localInvocationTargetException);
  }

  private static Long f(Context paramContext)
  {
    if (u == null)
      throw new u();
    try
    {
      Long localLong = (Long)u.invoke(null, new Object[] { paramContext });
      return localLong;
    }
    catch (IllegalAccessException localIllegalAccessException)
    {
      throw new u(localIllegalAccessException);
    }
    catch (InvocationTargetException localInvocationTargetException)
    {
    }
    throw new u(localInvocationTargetException);
  }

  private static String f()
  {
    if (m == null)
      throw new u();
    try
    {
      String str = (String)m.invoke(null, new Object[0]);
      return str;
    }
    catch (IllegalAccessException localIllegalAccessException)
    {
      throw new u(localIllegalAccessException);
    }
    catch (InvocationTargetException localInvocationTargetException)
    {
    }
    throw new u(localInvocationTargetException);
  }

  private static Long g()
  {
    if (l == null)
      throw new u();
    try
    {
      Long localLong = (Long)l.invoke(null, new Object[0]);
      return localLong;
    }
    catch (IllegalAccessException localIllegalAccessException)
    {
      throw new u(localIllegalAccessException);
    }
    catch (InvocationTargetException localInvocationTargetException)
    {
    }
    throw new u(localInvocationTargetException);
  }

  private static ArrayList g(Context paramContext)
  {
    if (r == null)
      throw new u();
    ArrayList localArrayList;
    try
    {
      localArrayList = (ArrayList)r.invoke(null, new Object[] { paramContext });
      if ((localArrayList == null) || (localArrayList.size() != 2))
        throw new u();
    }
    catch (IllegalAccessException localIllegalAccessException)
    {
      throw new u(localIllegalAccessException);
    }
    catch (InvocationTargetException localInvocationTargetException)
    {
      throw new u(localInvocationTargetException);
    }
    return localArrayList;
  }

  private static int[] h(Context paramContext)
  {
    if (s == null)
      throw new u();
    try
    {
      int[] arrayOfInt = (int[])s.invoke(null, new Object[] { paramContext });
      return arrayOfInt;
    }
    catch (IllegalAccessException localIllegalAccessException)
    {
      throw new u(localIllegalAccessException);
    }
    catch (InvocationTargetException localInvocationTargetException)
    {
    }
    throw new u(localInvocationTargetException);
  }

  private static int i(Context paramContext)
  {
    if (v == null)
      throw new u();
    try
    {
      int i = ((Integer)v.invoke(null, new Object[] { paramContext })).intValue();
      return i;
    }
    catch (IllegalAccessException localIllegalAccessException)
    {
      throw new u(localIllegalAccessException);
    }
    catch (InvocationTargetException localInvocationTargetException)
    {
    }
    throw new u(localInvocationTargetException);
  }

  private static int j(Context paramContext)
  {
    if (w == null)
      throw new u();
    try
    {
      int i = ((Integer)w.invoke(null, new Object[] { paramContext })).intValue();
      return i;
    }
    catch (IllegalAccessException localIllegalAccessException)
    {
      throw new u(localIllegalAccessException);
    }
    catch (InvocationTargetException localInvocationTargetException)
    {
    }
    throw new u(localInvocationTargetException);
  }

  // ERROR //
  protected com.google.ads.a.a.b b(Context paramContext)
  {
    // Byte code:
    //   0: new 453	com/google/ads/a/a/b
    //   3: dup
    //   4: invokespecial 454	com/google/ads/a/a/b:<init>	()V
    //   7: astore_2
    //   8: invokestatic 455	com/google/android/gms/b/t:b	()V
    //   11: getstatic 57	com/google/android/gms/b/t:F	Ljava/util/Random;
    //   14: invokevirtual 458	java/util/Random:nextInt	()I
    //   17: putstatic 460	com/google/android/gms/b/t:j	I
    //   20: iconst_0
    //   21: getstatic 460	com/google/android/gms/b/t:j	I
    //   24: invokestatic 462	com/google/android/gms/b/t:a	(II)V
    //   27: aload_2
    //   28: invokestatic 464	com/google/android/gms/b/t:f	()Ljava/lang/String;
    //   31: putfield 465	com/google/ads/a/a/b:a	Ljava/lang/String;
    //   34: iconst_1
    //   35: getstatic 460	com/google/android/gms/b/t:j	I
    //   38: invokestatic 462	com/google/android/gms/b/t:a	(II)V
    //   41: aload_2
    //   42: invokestatic 467	com/google/android/gms/b/t:d	()Ljava/lang/String;
    //   45: putfield 469	com/google/ads/a/a/b:b	Ljava/lang/String;
    //   48: iconst_2
    //   49: getstatic 460	com/google/android/gms/b/t:j	I
    //   52: invokestatic 462	com/google/android/gms/b/t:a	(II)V
    //   55: invokestatic 361	com/google/android/gms/b/t:e	()Ljava/lang/Long;
    //   58: invokevirtual 367	java/lang/Long:longValue	()J
    //   61: lstore 18
    //   63: aload_2
    //   64: lload 18
    //   66: invokestatic 473	java/lang/Long:valueOf	(J)Ljava/lang/Long;
    //   69: putfield 476	com/google/ads/a/a/b:D	Ljava/lang/Long;
    //   72: getstatic 46	com/google/android/gms/b/t:A	J
    //   75: lconst_0
    //   76: lcmp
    //   77: ifeq +26 -> 103
    //   80: aload_2
    //   81: lload 18
    //   83: getstatic 46	com/google/android/gms/b/t:A	J
    //   86: lsub
    //   87: invokestatic 473	java/lang/Long:valueOf	(J)Ljava/lang/Long;
    //   90: putfield 478	com/google/ads/a/a/b:j	Ljava/lang/Long;
    //   93: aload_2
    //   94: getstatic 46	com/google/android/gms/b/t:A	J
    //   97: invokestatic 473	java/lang/Long:valueOf	(J)Ljava/lang/Long;
    //   100: putfield 480	com/google/ads/a/a/b:l	Ljava/lang/Long;
    //   103: bipush 25
    //   105: getstatic 460	com/google/android/gms/b/t:j	I
    //   108: invokestatic 462	com/google/android/gms/b/t:a	(II)V
    //   111: aload_1
    //   112: invokestatic 482	com/google/android/gms/b/t:g	(Landroid/content/Context;)Ljava/util/ArrayList;
    //   115: astore 17
    //   117: aload_2
    //   118: aload 17
    //   120: iconst_0
    //   121: invokevirtual 486	java/util/ArrayList:get	(I)Ljava/lang/Object;
    //   124: checkcast 363	java/lang/Long
    //   127: invokevirtual 367	java/lang/Long:longValue	()J
    //   130: invokestatic 473	java/lang/Long:valueOf	(J)Ljava/lang/Long;
    //   133: putfield 488	com/google/ads/a/a/b:o	Ljava/lang/Long;
    //   136: aload_2
    //   137: aload 17
    //   139: iconst_1
    //   140: invokevirtual 486	java/util/ArrayList:get	(I)Ljava/lang/Object;
    //   143: checkcast 363	java/lang/Long
    //   146: invokevirtual 367	java/lang/Long:longValue	()J
    //   149: invokestatic 473	java/lang/Long:valueOf	(J)Ljava/lang/Long;
    //   152: putfield 490	com/google/ads/a/a/b:p	Ljava/lang/Long;
    //   155: bipush 31
    //   157: getstatic 460	com/google/android/gms/b/t:j	I
    //   160: invokestatic 462	com/google/android/gms/b/t:a	(II)V
    //   163: aload_2
    //   164: invokestatic 492	com/google/android/gms/b/t:g	()Ljava/lang/Long;
    //   167: putfield 494	com/google/ads/a/a/b:q	Ljava/lang/Long;
    //   170: bipush 33
    //   172: getstatic 460	com/google/android/gms/b/t:j	I
    //   175: invokestatic 462	com/google/android/gms/b/t:a	(II)V
    //   178: aload_2
    //   179: aload_1
    //   180: aload_0
    //   181: getfield 497	com/google/android/gms/b/t:h	Lcom/google/android/gms/b/A;
    //   184: invokestatic 499	com/google/android/gms/b/t:a	(Landroid/content/Context;Lcom/google/android/gms/b/A;)Ljava/lang/String;
    //   187: putfield 501	com/google/ads/a/a/b:m	Ljava/lang/String;
    //   190: bipush 27
    //   192: getstatic 460	com/google/android/gms/b/t:j	I
    //   195: invokestatic 462	com/google/android/gms/b/t:a	(II)V
    //   198: aload_2
    //   199: aload_1
    //   200: aload_0
    //   201: getfield 497	com/google/android/gms/b/t:h	Lcom/google/android/gms/b/A;
    //   204: invokestatic 503	com/google/android/gms/b/t:b	(Landroid/content/Context;Lcom/google/android/gms/b/A;)Ljava/lang/String;
    //   207: putfield 505	com/google/ads/a/a/b:n	Ljava/lang/String;
    //   210: bipush 29
    //   212: getstatic 460	com/google/android/gms/b/t:j	I
    //   215: invokestatic 462	com/google/android/gms/b/t:a	(II)V
    //   218: aload_1
    //   219: invokestatic 507	com/google/android/gms/b/t:h	(Landroid/content/Context;)[I
    //   222: astore 16
    //   224: aload_2
    //   225: aload 16
    //   227: iconst_0
    //   228: iaload
    //   229: i2l
    //   230: invokestatic 473	java/lang/Long:valueOf	(J)Ljava/lang/Long;
    //   233: putfield 509	com/google/ads/a/a/b:d	Ljava/lang/Long;
    //   236: aload_2
    //   237: aload 16
    //   239: iconst_1
    //   240: iaload
    //   241: i2l
    //   242: invokestatic 473	java/lang/Long:valueOf	(J)Ljava/lang/Long;
    //   245: putfield 511	com/google/ads/a/a/b:e	Ljava/lang/Long;
    //   248: iconst_5
    //   249: getstatic 460	com/google/android/gms/b/t:j	I
    //   252: invokestatic 462	com/google/android/gms/b/t:a	(II)V
    //   255: aload_2
    //   256: aload_1
    //   257: invokestatic 513	com/google/android/gms/b/t:i	(Landroid/content/Context;)I
    //   260: i2l
    //   261: invokestatic 473	java/lang/Long:valueOf	(J)Ljava/lang/Long;
    //   264: putfield 515	com/google/ads/a/a/b:f	Ljava/lang/Long;
    //   267: bipush 12
    //   269: getstatic 460	com/google/android/gms/b/t:j	I
    //   272: invokestatic 462	com/google/android/gms/b/t:a	(II)V
    //   275: aload_2
    //   276: aload_1
    //   277: invokestatic 517	com/google/android/gms/b/t:j	(Landroid/content/Context;)I
    //   280: i2l
    //   281: invokestatic 473	java/lang/Long:valueOf	(J)Ljava/lang/Long;
    //   284: putfield 519	com/google/ads/a/a/b:c	Ljava/lang/Long;
    //   287: iconst_3
    //   288: getstatic 460	com/google/android/gms/b/t:j	I
    //   291: invokestatic 462	com/google/android/gms/b/t:a	(II)V
    //   294: aload_2
    //   295: aload_1
    //   296: invokestatic 521	com/google/android/gms/b/t:e	(Landroid/content/Context;)Ljava/lang/String;
    //   299: putfield 523	com/google/ads/a/a/b:r	Ljava/lang/String;
    //   302: bipush 34
    //   304: getstatic 460	com/google/android/gms/b/t:j	I
    //   307: invokestatic 462	com/google/android/gms/b/t:a	(II)V
    //   310: aload_2
    //   311: aload_1
    //   312: invokestatic 525	com/google/android/gms/b/t:f	(Landroid/content/Context;)Ljava/lang/Long;
    //   315: putfield 527	com/google/ads/a/a/b:s	Ljava/lang/Long;
    //   318: bipush 35
    //   320: getstatic 460	com/google/android/gms/b/t:j	I
    //   323: invokestatic 462	com/google/android/gms/b/t:a	(II)V
    //   326: invokestatic 528	com/google/android/gms/b/t:c	()V
    //   329: aload_2
    //   330: areturn
    //   331: astore_3
    //   332: aload_2
    //   333: areturn
    //   334: astore 15
    //   336: goto -10 -> 326
    //   339: astore 14
    //   341: goto -31 -> 310
    //   344: astore 13
    //   346: goto -52 -> 294
    //   349: astore 12
    //   351: goto -76 -> 275
    //   354: astore 11
    //   356: goto -101 -> 255
    //   359: astore 10
    //   361: goto -143 -> 218
    //   364: astore 9
    //   366: goto -168 -> 198
    //   369: astore 8
    //   371: goto -193 -> 178
    //   374: astore 7
    //   376: goto -213 -> 163
    //   379: astore 6
    //   381: goto -270 -> 111
    //   384: astore 5
    //   386: goto -331 -> 55
    //   389: astore 4
    //   391: goto -350 -> 41
    //
    // Exception table:
    //   from	to	target	type
    //   8	27	331	java/io/IOException
    //   27	41	331	java/io/IOException
    //   41	55	331	java/io/IOException
    //   55	103	331	java/io/IOException
    //   103	111	331	java/io/IOException
    //   111	163	331	java/io/IOException
    //   163	178	331	java/io/IOException
    //   178	198	331	java/io/IOException
    //   198	218	331	java/io/IOException
    //   218	255	331	java/io/IOException
    //   255	275	331	java/io/IOException
    //   275	294	331	java/io/IOException
    //   294	310	331	java/io/IOException
    //   310	326	331	java/io/IOException
    //   326	329	331	java/io/IOException
    //   310	326	334	com/google/android/gms/b/u
    //   294	310	339	com/google/android/gms/b/u
    //   275	294	344	com/google/android/gms/b/u
    //   255	275	349	com/google/android/gms/b/u
    //   218	255	354	com/google/android/gms/b/u
    //   198	218	359	com/google/android/gms/b/u
    //   178	198	364	com/google/android/gms/b/u
    //   163	178	369	com/google/android/gms/b/u
    //   111	163	374	com/google/android/gms/b/u
    //   55	103	379	com/google/android/gms/b/u
    //   103	111	379	com/google/android/gms/b/u
    //   41	55	384	com/google/android/gms/b/u
    //   27	41	389	com/google/android/gms/b/u
  }

  // ERROR //
  protected final com.google.ads.a.a.b c(Context paramContext)
  {
    // Byte code:
    //   0: iconst_0
    //   1: istore_2
    //   2: new 453	com/google/ads/a/a/b
    //   5: dup
    //   6: invokespecial 454	com/google/ads/a/a/b:<init>	()V
    //   9: astore_3
    //   10: invokestatic 455	com/google/android/gms/b/t:b	()V
    //   13: getstatic 57	com/google/android/gms/b/t:F	Ljava/util/Random;
    //   16: invokevirtual 458	java/util/Random:nextInt	()I
    //   19: putstatic 460	com/google/android/gms/b/t:j	I
    //   22: aload_3
    //   23: invokestatic 467	com/google/android/gms/b/t:d	()Ljava/lang/String;
    //   26: putfield 469	com/google/ads/a/a/b:b	Ljava/lang/String;
    //   29: aload_3
    //   30: invokestatic 464	com/google/android/gms/b/t:f	()Ljava/lang/String;
    //   33: putfield 465	com/google/ads/a/a/b:a	Ljava/lang/String;
    //   36: aload_3
    //   37: invokestatic 361	com/google/android/gms/b/t:e	()Ljava/lang/Long;
    //   40: putfield 476	com/google/ads/a/a/b:D	Ljava/lang/Long;
    //   43: iconst_0
    //   44: getstatic 460	com/google/android/gms/b/t:j	I
    //   47: invokestatic 462	com/google/android/gms/b/t:a	(II)V
    //   50: aload_0
    //   51: getfield 531	com/google/android/gms/b/t:a	Landroid/view/MotionEvent;
    //   54: aload_0
    //   55: getfield 534	com/google/android/gms/b/t:g	Landroid/util/DisplayMetrics;
    //   58: invokestatic 536	com/google/android/gms/b/t:a	(Landroid/view/MotionEvent;Landroid/util/DisplayMetrics;)Ljava/util/ArrayList;
    //   61: astore 15
    //   63: aload_3
    //   64: aload 15
    //   66: iconst_0
    //   67: invokevirtual 486	java/util/ArrayList:get	(I)Ljava/lang/Object;
    //   70: checkcast 363	java/lang/Long
    //   73: putfield 538	com/google/ads/a/a/b:g	Ljava/lang/Long;
    //   76: aload_3
    //   77: aload 15
    //   79: iconst_1
    //   80: invokevirtual 486	java/util/ArrayList:get	(I)Ljava/lang/Object;
    //   83: checkcast 363	java/lang/Long
    //   86: putfield 540	com/google/ads/a/a/b:h	Ljava/lang/Long;
    //   89: aload 15
    //   91: iconst_2
    //   92: invokevirtual 486	java/util/ArrayList:get	(I)Ljava/lang/Object;
    //   95: checkcast 363	java/lang/Long
    //   98: invokevirtual 367	java/lang/Long:longValue	()J
    //   101: lconst_0
    //   102: lcmp
    //   103: iflt +16 -> 119
    //   106: aload_3
    //   107: aload 15
    //   109: iconst_2
    //   110: invokevirtual 486	java/util/ArrayList:get	(I)Ljava/lang/Object;
    //   113: checkcast 363	java/lang/Long
    //   116: putfield 542	com/google/ads/a/a/b:i	Ljava/lang/Long;
    //   119: aload_3
    //   120: aload 15
    //   122: iconst_3
    //   123: invokevirtual 486	java/util/ArrayList:get	(I)Ljava/lang/Object;
    //   126: checkcast 363	java/lang/Long
    //   129: putfield 544	com/google/ads/a/a/b:t	Ljava/lang/Long;
    //   132: aload_3
    //   133: aload 15
    //   135: iconst_4
    //   136: invokevirtual 486	java/util/ArrayList:get	(I)Ljava/lang/Object;
    //   139: checkcast 363	java/lang/Long
    //   142: putfield 546	com/google/ads/a/a/b:u	Ljava/lang/Long;
    //   145: bipush 14
    //   147: getstatic 460	com/google/android/gms/b/t:j	I
    //   150: invokestatic 462	com/google/android/gms/b/t:a	(II)V
    //   153: aload_0
    //   154: getfield 548	com/google/android/gms/b/t:c	J
    //   157: lconst_0
    //   158: lcmp
    //   159: ifle +14 -> 173
    //   162: aload_3
    //   163: aload_0
    //   164: getfield 548	com/google/android/gms/b/t:c	J
    //   167: invokestatic 473	java/lang/Long:valueOf	(J)Ljava/lang/Long;
    //   170: putfield 550	com/google/ads/a/a/b:x	Ljava/lang/Long;
    //   173: aload_0
    //   174: getfield 552	com/google/android/gms/b/t:d	J
    //   177: lconst_0
    //   178: lcmp
    //   179: ifle +14 -> 193
    //   182: aload_3
    //   183: aload_0
    //   184: getfield 552	com/google/android/gms/b/t:d	J
    //   187: invokestatic 473	java/lang/Long:valueOf	(J)Ljava/lang/Long;
    //   190: putfield 554	com/google/ads/a/a/b:w	Ljava/lang/Long;
    //   193: aload_0
    //   194: getfield 556	com/google/android/gms/b/t:e	J
    //   197: lconst_0
    //   198: lcmp
    //   199: ifle +14 -> 213
    //   202: aload_3
    //   203: aload_0
    //   204: getfield 556	com/google/android/gms/b/t:e	J
    //   207: invokestatic 473	java/lang/Long:valueOf	(J)Ljava/lang/Long;
    //   210: putfield 558	com/google/ads/a/a/b:v	Ljava/lang/Long;
    //   213: aload_0
    //   214: getfield 560	com/google/android/gms/b/t:f	J
    //   217: lconst_0
    //   218: lcmp
    //   219: ifle +14 -> 233
    //   222: aload_3
    //   223: aload_0
    //   224: getfield 560	com/google/android/gms/b/t:f	J
    //   227: invokestatic 473	java/lang/Long:valueOf	(J)Ljava/lang/Long;
    //   230: putfield 562	com/google/ads/a/a/b:y	Ljava/lang/Long;
    //   233: iconst_m1
    //   234: aload_0
    //   235: getfield 565	com/google/android/gms/b/t:b	Ljava/util/LinkedList;
    //   238: invokevirtual 568	java/util/LinkedList:size	()I
    //   241: iadd
    //   242: istore 12
    //   244: iload 12
    //   246: ifle +96 -> 342
    //   249: aload_3
    //   250: iload 12
    //   252: anewarray 570	com/google/ads/a/a/c
    //   255: putfield 573	com/google/ads/a/a/b:z	[Lcom/google/ads/a/a/c;
    //   258: iload_2
    //   259: iload 12
    //   261: if_icmpge +81 -> 342
    //   264: aload_0
    //   265: getfield 565	com/google/android/gms/b/t:b	Ljava/util/LinkedList;
    //   268: iload_2
    //   269: invokevirtual 574	java/util/LinkedList:get	(I)Ljava/lang/Object;
    //   272: checkcast 307	android/view/MotionEvent
    //   275: aload_0
    //   276: getfield 534	com/google/android/gms/b/t:g	Landroid/util/DisplayMetrics;
    //   279: invokestatic 536	com/google/android/gms/b/t:a	(Landroid/view/MotionEvent;Landroid/util/DisplayMetrics;)Ljava/util/ArrayList;
    //   282: astore 13
    //   284: new 570	com/google/ads/a/a/c
    //   287: dup
    //   288: invokespecial 575	com/google/ads/a/a/c:<init>	()V
    //   291: astore 14
    //   293: aload 14
    //   295: aload 13
    //   297: iconst_0
    //   298: invokevirtual 486	java/util/ArrayList:get	(I)Ljava/lang/Object;
    //   301: checkcast 363	java/lang/Long
    //   304: putfield 577	com/google/ads/a/a/c:a	Ljava/lang/Long;
    //   307: aload 14
    //   309: aload 13
    //   311: iconst_1
    //   312: invokevirtual 486	java/util/ArrayList:get	(I)Ljava/lang/Object;
    //   315: checkcast 363	java/lang/Long
    //   318: putfield 579	com/google/ads/a/a/c:b	Ljava/lang/Long;
    //   321: aload_3
    //   322: getfield 573	com/google/ads/a/a/b:z	[Lcom/google/ads/a/a/c;
    //   325: iload_2
    //   326: aload 14
    //   328: aastore
    //   329: iinc 2 1
    //   332: goto -74 -> 258
    //   335: astore 9
    //   337: aload_3
    //   338: aconst_null
    //   339: putfield 573	com/google/ads/a/a/b:z	[Lcom/google/ads/a/a/c;
    //   342: aload_3
    //   343: aload_1
    //   344: invokestatic 521	com/google/android/gms/b/t:e	(Landroid/content/Context;)Ljava/lang/String;
    //   347: putfield 523	com/google/ads/a/a/b:r	Ljava/lang/String;
    //   350: aload_3
    //   351: aload_1
    //   352: invokestatic 525	com/google/android/gms/b/t:f	(Landroid/content/Context;)Ljava/lang/Long;
    //   355: putfield 527	com/google/ads/a/a/b:s	Ljava/lang/Long;
    //   358: invokestatic 528	com/google/android/gms/b/t:c	()V
    //   361: aload_3
    //   362: areturn
    //   363: astore 4
    //   365: aload_3
    //   366: areturn
    //   367: astore 11
    //   369: goto -11 -> 358
    //   372: astore 10
    //   374: goto -24 -> 350
    //   377: astore 8
    //   379: goto -226 -> 153
    //   382: astore 7
    //   384: goto -341 -> 43
    //   387: astore 6
    //   389: goto -353 -> 36
    //   392: astore 5
    //   394: goto -365 -> 29
    //
    // Exception table:
    //   from	to	target	type
    //   233	244	335	com/google/android/gms/b/u
    //   249	258	335	com/google/android/gms/b/u
    //   264	329	335	com/google/android/gms/b/u
    //   10	22	363	java/io/IOException
    //   22	29	363	java/io/IOException
    //   29	36	363	java/io/IOException
    //   36	43	363	java/io/IOException
    //   43	50	363	java/io/IOException
    //   50	119	363	java/io/IOException
    //   119	153	363	java/io/IOException
    //   153	173	363	java/io/IOException
    //   173	193	363	java/io/IOException
    //   193	213	363	java/io/IOException
    //   213	233	363	java/io/IOException
    //   233	244	363	java/io/IOException
    //   249	258	363	java/io/IOException
    //   264	329	363	java/io/IOException
    //   337	342	363	java/io/IOException
    //   342	350	363	java/io/IOException
    //   350	358	363	java/io/IOException
    //   358	361	363	java/io/IOException
    //   350	358	367	com/google/android/gms/b/u
    //   342	350	372	com/google/android/gms/b/u
    //   50	119	377	com/google/android/gms/b/u
    //   119	153	377	com/google/android/gms/b/u
    //   36	43	382	com/google/android/gms/b/u
    //   29	36	387	com/google/android/gms/b/u
    //   22	29	392	com/google/android/gms/b/u
  }
}

/* Location:           C:\Users\KSHITIZ GUPTA\Downloads\apktool-install-windws\dex2jar-0.0.9.15\dex2jar-0.0.9.15\classes_dex2jar.jar
 * Qualified Name:     com.google.android.gms.b.t
 * JD-Core Version:    0.6.0
 */