package com.google.android.gms.b;

import android.content.Context;

final class x
  implements Runnable
{
  private Context a;

  public x(Context paramContext)
  {
    this.a = paramContext.getApplicationContext();
    if (this.a == null)
      this.a = paramContext;
  }

  // ERROR //
  public final void run()
  {
    // Byte code:
    //   0: ldc 30
    //   2: monitorenter
    //   3: invokestatic 34	com/google/android/gms/b/v:b	()Lcom/google/android/gms/ads/c/a;
    //   6: ifnonnull +27 -> 33
    //   9: new 36	com/google/android/gms/ads/c/a
    //   12: dup
    //   13: aload_0
    //   14: getfield 21	com/google/android/gms/b/x:a	Landroid/content/Context;
    //   17: invokespecial 38	com/google/android/gms/ads/c/a:<init>	(Landroid/content/Context;)V
    //   20: astore 7
    //   22: aload 7
    //   24: invokevirtual 40	com/google/android/gms/ads/c/a:a	()V
    //   27: aload 7
    //   29: invokestatic 43	com/google/android/gms/b/v:a	(Lcom/google/android/gms/ads/c/a;)Lcom/google/android/gms/ads/c/a;
    //   32: pop
    //   33: invokestatic 47	com/google/android/gms/b/v:c	()Ljava/util/concurrent/CountDownLatch;
    //   36: invokevirtual 52	java/util/concurrent/CountDownLatch:countDown	()V
    //   39: ldc 30
    //   41: monitorexit
    //   42: return
    //   43: astore 6
    //   45: aconst_null
    //   46: invokestatic 43	com/google/android/gms/b/v:a	(Lcom/google/android/gms/ads/c/a;)Lcom/google/android/gms/ads/c/a;
    //   49: pop
    //   50: invokestatic 47	com/google/android/gms/b/v:c	()Ljava/util/concurrent/CountDownLatch;
    //   53: invokevirtual 52	java/util/concurrent/CountDownLatch:countDown	()V
    //   56: goto -17 -> 39
    //   59: astore_3
    //   60: ldc 30
    //   62: monitorexit
    //   63: aload_3
    //   64: athrow
    //   65: astore_2
    //   66: invokestatic 47	com/google/android/gms/b/v:c	()Ljava/util/concurrent/CountDownLatch;
    //   69: invokevirtual 52	java/util/concurrent/CountDownLatch:countDown	()V
    //   72: aload_2
    //   73: athrow
    //   74: astore 5
    //   76: goto -31 -> 45
    //   79: astore_1
    //   80: goto -35 -> 45
    //
    // Exception table:
    //   from	to	target	type
    //   3	33	43	com/google/android/gms/common/c
    //   33	39	59	finally
    //   39	42	59	finally
    //   50	56	59	finally
    //   60	63	59	finally
    //   66	74	59	finally
    //   3	33	65	finally
    //   45	50	65	finally
    //   3	33	74	com/google/android/gms/common/d
    //   3	33	79	java/io/IOException
  }
}

/* Location:           C:\Users\KSHITIZ GUPTA\Downloads\apktool-install-windws\dex2jar-0.0.9.15\dex2jar-0.0.9.15\classes_dex2jar.jar
 * Qualified Name:     com.google.android.gms.b.x
 * JD-Core Version:    0.6.0
 */